{
    "id": 18393,
    "date": "2020-06-01T05:00:00",
    "date_gmt": "2020-06-01T12:00:00",
    "guid": {
        "rendered": "http://estreetshuffle.com/?p=18393"
    },
    "modified": "2020-06-01T05:09:49",
    "modified_gmt": "2020-06-01T12:09:49",
    "slug": "matr-michael-strollo-and-bruce-springsteen-could-die-young-tonight",
    "status": "publish",
    "type": "post",
    "link": "https://estreetshuffle.com/index.php/2020/06/01/matr-michael-strollo-and-bruce-springsteen-could-die-young-tonight/",
    "title": {
        "rendered": "MatR: Michael Strollo and Bruce Springsteen: Could Die Young Tonight"
    },
    "content": {
        "rendered": "<p>In the early 2000s, Michael Strollo made a local name for himself as the lead singer of Exit 105, a terrific Jersey Shore-based rock band. (Where else would a band with that name be from?)</p>\n<p>Strollo went solo in 2008 and released his first album,\u00a0<em>Bedroom Eyes,\u00a0</em>in 2010. Among the standout songs on that album is a sad, beautiful ballad called &#8220;Could Die Young Tonight.&#8221;</p>\n<div class=\"jetpack-video-wrapper\"><span class=\"embed-youtube\" style=\"text-align:center; display: block;\"><iframe loading=\"lazy\" class=\"youtube-player\" width=\"758\" height=\"427\" src=\"https://www.youtube.com/embed/SYn3Jp8Gqbc?version=3&#038;rel=1&#038;showsearch=0&#038;showinfo=1&#038;iv_load_policy=1&#038;fs=1&#038;hl=en-US&#038;autohide=2&#038;wmode=transparent\" allowfullscreen=\"true\" style=\"border:0;\" sandbox=\"allow-scripts allow-same-origin allow-popups allow-presentation\"></iframe></span></div>\n<p>Although Exit 105 had already <a href=\"http://estreetshuffle.com/index.php/2019/12/02/kingdom-of-days-december-2-2/\">once shared a stage with Bruce</a> (at Joe Grushecky&#8217;s 2004 Flood Aid concert in Pittsburgh), Strollo probably never imagined he&#8217;d have the opportunity to do so again as a singer-songwriter. And given the circumstances that led to it, he certainly wouldn&#8217;t have wished for it.</p>\n<p>In early 2012, Bruce&#8217;s long-time personal trainer died suddenly at the age of 40, and on the night of February 25th, Tony Strollo&#8217;s friends and family turned out at the Press Room in Asbury Park to celebrate his too-short life. Bruce was one of Tony&#8217;s friends in attendance, and Michael was part of the family.</p>\n<p>To celebrate his brother, Michael performed &#8220;Could Die Young Tonight,&#8221; and Bruce joined him on stage to support him on acoustic guitar.</p>\n<p>Here&#8217;s their poignant, one-time-only performance of &#8220;Could Die Young Tonight.&#8221;</p>\n<div class=\"jetpack-video-wrapper\"><span class=\"embed-youtube\" style=\"text-align:center; display: block;\"><iframe loading=\"lazy\" class=\"youtube-player\" width=\"758\" height=\"427\" src=\"https://www.youtube.com/embed/d9Lw3sUj-Q8?version=3&#038;rel=1&#038;showsearch=0&#038;showinfo=1&#038;iv_load_policy=1&#038;fs=1&#038;hl=en-US&#038;autohide=2&#038;wmode=transparent\" allowfullscreen=\"true\" style=\"border:0;\" sandbox=\"allow-scripts allow-same-origin allow-popups allow-presentation\"></iframe></span></div>\n<p><strong>Could Die Young Tonight<br />\nFirst performed:</strong> February 25, 2012 (Asbury Park, NJ)<br />\n<strong>Last performed:</strong> February 25, 2012 (Asbury Park, NJ)</p>\n<p>&nbsp;</p>\n",
        "protected": false
    },
    "excerpt": {
        "rendered": "<p>One time only: Bruce joins Michael Strollo on &#8220;Could Die Young Tonight&#8221; to pay tribute to Michael&#8217;s recently departed brother (and Bruce&#8217;s friend), Tony.</p>\n",
        "protected": false
    },
    "author": 1,
    "featured_media": 18736,
    "comment_status": "open",
    "ping_status": "open",
    "sticky": false,
    "template": "",
    "format": "standard",
    "meta": {
        "_mi_skip_tracking": false,
        "jetpack_post_was_ever_published": false,
        "jetpack_publicize_message": "",
        "jetpack_is_tweetstorm": false,
        "jetpack_publicize_feature_enabled": true,
        "jetpack_social_post_already_shared": true,
        "jetpack_social_options": []
    },
    "categories": [
        4,
        5
    ],
    "tags": [
        2767,
        1943,
        2200
    ],
    "jetpack_publicize_connections": [],
    "aioseo_notices": [],
    "jetpack_featured_media_url": "https://i0.wp.com/estreetshuffle.com/wp-content/uploads/2020/05/dieyoung.jpg?fit=500%2C500&ssl=1",
    "jetpack_sharing_enabled": true,
    "jetpack_shortlink": "https://wp.me/p9w3Lk-4MF",
    "jetpack_likes_enabled": true,
    "jetpack-related-posts": [
        {
            "id": 41859,
            "url": "https://estreetshuffle.com/index.php/2023/02/25/kingdom-of-days-february-25-2/",
            "url_meta": {
                "origin": 18393,
                "position": 0
            },
            "title": "Kingdom of Days: February 25",
            "date": "February 25, 2023",
            "format": false,
            "excerpt": "On this day in Springsteen history: The Tunnel of Love Express Tour kicks off, the E Street Band plays their last concert to date, the inspiration for one of Bruce's most controversial songs, and a whole lot more.",
            "rel": "",
            "context": "In &quot;Kingdom of Days&quot;",
            "img": {
                "alt_text": "",
                "src": "https://i0.wp.com/estreetshuffle.com/wp-content/uploads/2018/02/TOL-Express.jpg?fit=800%2C800&ssl=1&resize=350%2C200",
                "width": 350,
                "height": 200
            },
            "classes": []
        },
        {
            "id": 19804,
            "url": "https://estreetshuffle.com/index.php/2020/08/13/matr-bruce-springsteen-neil-young-and-exit-105-all-along-the-watchtower/",
            "url_meta": {
                "origin": 18393,
                "position": 1
            },
            "title": "MatR: Bruce Springsteen, Neil Young, and Exit 105: All Along the Watchtower",
            "date": "August 13, 2020",
            "format": false,
            "excerpt": "First with Neil Young, then with Exit 105, Bruce turns in covers of Bob Dylan's classic that are epic in both length and intensity.",
            "rel": "",
            "context": "In &quot;Cover Me&quot;",
            "img": {
                "alt_text": "",
                "src": "https://i0.wp.com/estreetshuffle.com/wp-content/uploads/2020/07/bob-dylan-all-along-the-watchtower-cbs-3.jpg?fit=640%2C637&ssl=1&resize=350%2C200",
                "width": 350,
                "height": 200
            },
            "classes": []
        },
        {
            "id": 16062,
            "url": "https://estreetshuffle.com/index.php/2020/02/10/matr-billy-joel-bruce-springsteen-and-the-e-street-band-only-the-good-die-young/",
            "url_meta": {
                "origin": 18393,
                "position": 2
            },
            "title": "MatR: Billy Joel, Bruce Springsteen and the E Street Band: Only the Good Die Young",
            "date": "February 10, 2020",
            "format": false,
            "excerpt": "One time only: Bruce joins Billy Joel on stage at the Rock and Roll Hall of Fame 25th Anniversary Concert for Billy's Top 40 hit, \"Only the Good Die Young.\"",
            "rel": "",
            "context": "In &quot;Cover Me&quot;",
            "img": {
                "alt_text": "",
                "src": "https://i0.wp.com/estreetshuffle.com/wp-content/uploads/2020/02/onlythegood.jpg?fit=793%2C800&ssl=1&resize=350%2C200",
                "width": 350,
                "height": 200
            },
            "classes": []
        },
        {
            "id": 39567,
            "url": "https://estreetshuffle.com/index.php/2022/12/02/kingdom-of-days-december-2/",
            "url_meta": {
                "origin": 18393,
                "position": 3
            },
            "title": "Kingdom of Days: December 2",
            "date": "December 2, 2022",
            "format": false,
            "excerpt": "On this date: Bruce teams up with Joe Grushecky, Robert Gordon, Dion, and Marah. Plus: the earliest recorded \"Santa Claus is Comin' to Town,\" and more.",
            "rel": "",
            "context": "In &quot;Kingdom of Days&quot;",
            "img": {
                "alt_text": "",
                "src": "https://i0.wp.com/estreetshuffle.com/wp-content/uploads/2019/11/19801202_2_front.jpg?fit=1077%2C941&ssl=1&resize=350%2C200",
                "width": 350,
                "height": 200
            },
            "classes": []
        },
        {
            "id": 38930,
            "url": "https://estreetshuffle.com/index.php/2022/11/01/kingdom-of-days-november-1/",
            "url_meta": {
                "origin": 18393,
                "position": 4
            },
            "title": "Kingdom of Days: November 1",
            "date": "November 1, 2022",
            "format": false,
            "excerpt": "Child plays their last show, \"The Ties That Bind\" and \"Fade Away\" make their debut, and the first all-Bruce, all-the-time radio station takes to the airwaves.",
            "rel": "",
            "context": "In &quot;Kingdom of Days&quot;",
            "img": {
                "alt_text": "",
                "src": "https://i0.wp.com/estreetshuffle.com/wp-content/uploads/2021/11/i_pilarz_sirius.jpg?fit=1200%2C681&ssl=1&resize=350%2C200",
                "width": 350,
                "height": 200
            },
            "classes": []
        },
        {
            "id": 40715,
            "url": "https://estreetshuffle.com/index.php/2023/01/09/kingdom-of-days-january-9/",
            "url_meta": {
                "origin": 18393,
                "position": 5
            },
            "title": "Kingdom of Days: January 9",
            "date": "January 9, 2023",
            "format": false,
            "excerpt": "On this date: listen to the earliest live recording of Bruce and the E Street Band, a full performance of Springsteen on Broadway, and more.",
            "rel": "",
            "context": "In &quot;Kingdom of Days&quot;",
            "img": {
                "alt_text": "",
                "src": "https://i0.wp.com/estreetshuffle.com/wp-content/uploads/2019/12/19730109_front.jpg?fit=800%2C800&ssl=1&resize=350%2C200",
                "width": 350,
                "height": 200
            },
            "classes": []
        }
    ],
    "_links": {
        "self": [
            {
                "href": "https://estreetshuffle.com/index.php/wp-json/wp/v2/posts/18393"
            }
        ],
        "collection": [
            {
                "href": "https://estreetshuffle.com/index.php/wp-json/wp/v2/posts"
            }
        ],
        "about": [
            {
                "href": "https://estreetshuffle.com/index.php/wp-json/wp/v2/types/post"
            }
        ],
        "author": [
            {
                "embeddable": true,
                "href": "https://estreetshuffle.com/index.php/wp-json/wp/v2/users/1"
            }
        ],
        "replies": [
            {
                "embeddable": true,
                "href": "https://estreetshuffle.com/index.php/wp-json/wp/v2/comments?post=18393"
            }
        ],
        "version-history": [
            {
                "count": 5,
                "href": "https://estreetshuffle.com/index.php/wp-json/wp/v2/posts/18393/revisions"
            }
        ],
        "predecessor-version": [
            {
                "id": 18963,
                "href": "https://estreetshuffle.com/index.php/wp-json/wp/v2/posts/18393/revisions/18963"
            }
        ],
        "wp:featuredmedia": [
            {
                "embeddable": true,
                "href": "https://estreetshuffle.com/index.php/wp-json/wp/v2/media/18736"
            }
        ],
        "wp:attachment": [
            {
                "href": "https://estreetshuffle.com/index.php/wp-json/wp/v2/media?parent=18393"
            }
        ],
        "wp:term": [
            {
                "taxonomy": "category",
                "embeddable": true,
                "href": "https://estreetshuffle.com/index.php/wp-json/wp/v2/categories?post=18393"
            },
            {
                "taxonomy": "post_tag",
                "embeddable": true,
                "href": "https://estreetshuffle.com/index.php/wp-json/wp/v2/tags?post=18393"
            }
        ],
        "curies": [
            {
                "name": "wp",
                "href": "https://api.w.org/{rel}",
                "templated": true
            }
        ]
    }
}