[{"id": 3331, "count": 1, "description": "", "link": "https://estreetshuffle.com/index.php/tag/marie/", "name": "Marie", "slug": "marie", "taxonomy": "post_tag", "meta": [], "_links": {"self": [{"href": "https://estreetshuffle.com/index.php/wp-json/wp/v2/tags/3331", "targetHints": {"allow": ["GET"]}}], "collection": [{"href": "https://estreetshuffle.com/index.php/wp-json/wp/v2/tags"}], "about": [{"href": "https://estreetshuffle.com/index.php/wp-json/wp/v2/taxonomies/post_tag"}], "wp:post_type": [{"href": "https://estreetshuffle.com/index.php/wp-json/wp/v2/posts?tags=3331"}, {"href": "https://estreetshuffle.com/index.php/wp-json/wp/v2/pages?tags=3331"}, {"href": "https://estreetshuffle.com/index.php/wp-json/wp/v2/jetpack-portfolio?tags=3331"}], "curies": [{"name": "wp", "href": "https://api.w.org/{rel}", "templated": true}]}}, {"id": 2991, "count": 1, "description": "", "link": "https://estreetshuffle.com/index.php/tag/marietta-phillips/", "name": "Marietta Phillips", "slug": "marietta-phillips", "taxonomy": "post_tag", "meta": [], "_links": {"self": [{"href": "https://estreetshuffle.com/index.php/wp-json/wp/v2/tags/2991", "targetHints": {"allow": ["GET"]}}], "collection": [{"href": "https://estreetshuffle.com/index.php/wp-json/wp/v2/tags"}], "about": [{"href": "https://estreetshuffle.com/index.php/wp-json/wp/v2/taxonomies/post_tag"}], "wp:post_type": [{"href": "https://estreetshuffle.com/index.php/wp-json/wp/v2/posts?tags=2991"}, {"href": "https://estreetshuffle.com/index.php/wp-json/wp/v2/pages?tags=2991"}, {"href": "https://estreetshuffle.com/index.php/wp-json/wp/v2/jetpack-portfolio?tags=2991"}], "curies": [{"name": "wp", "href": "https://api.w.org/{rel}", "templated": true}]}}, {"id": 2411, "count": 1, "description": "", "link": "https://estreetshuffle.com/index.php/tag/mark-cunningham/", "name": "Mark Cunningham", "slug": "mark-cunningham", "taxonomy": "post_tag", "meta": [], "_links": {"self": [{"href": "https://estreetshuffle.com/index.php/wp-json/wp/v2/tags/2411", "targetHints": {"allow": ["GET"]}}], "collection": [{"href": "https://estreetshuffle.com/index.php/wp-json/wp/v2/tags"}], "about": [{"href": "https://estreetshuffle.com/index.php/wp-json/wp/v2/taxonomies/post_tag"}], "wp:post_type": [{"href": "https://estreetshuffle.com/index.php/wp-json/wp/v2/posts?tags=2411"}, {"href": "https://estreetshuffle.com/index.php/wp-json/wp/v2/pages?tags=2411"}, {"href": "https://estreetshuffle.com/index.php/wp-json/wp/v2/jetpack-portfolio?tags=2411"}], "curies": [{"name": "wp", "href": "https://api.w.org/{rel}", "templated": true}]}}, {"id": 2210, "count": 1, "description": "", "link": "https://estreetshuffle.com/index.php/tag/mark-james/", "name": "Mark James", "slug": "mark-james", "taxonomy": "post_tag", "meta": [], "_links": {"self": [{"href": "https://estreetshuffle.com/index.php/wp-json/wp/v2/tags/2210", "targetHints": {"allow": ["GET"]}}], "collection": [{"href": "https://estreetshuffle.com/index.php/wp-json/wp/v2/tags"}], "about": [{"href": "https://estreetshuffle.com/index.php/wp-json/wp/v2/taxonomies/post_tag"}], "wp:post_type": [{"href": "https://estreetshuffle.com/index.php/wp-json/wp/v2/posts?tags=2210"}, {"href": "https://estreetshuffle.com/index.php/wp-json/wp/v2/pages?tags=2210"}, {"href": "https://estreetshuffle.com/index.php/wp-json/wp/v2/jetpack-portfolio?tags=2210"}], "curies": [{"name": "wp", "href": "https://api.w.org/{rel}", "templated": true}]}}, {"id": 2656, "count": 1, "description": "", "link": "https://estreetshuffle.com/index.php/tag/mark-lavengood-band/", "name": "Mark Lavengood Band", "slug": "mark-lavengood-band", "taxonomy": "post_tag", "meta": [], "_links": {"self": [{"href": "https://estreetshuffle.com/index.php/wp-json/wp/v2/tags/2656", "targetHints": {"allow": ["GET"]}}], "collection": [{"href": "https://estreetshuffle.com/index.php/wp-json/wp/v2/tags"}], "about": [{"href": "https://estreetshuffle.com/index.php/wp-json/wp/v2/taxonomies/post_tag"}], "wp:post_type": [{"href": "https://estreetshuffle.com/index.php/wp-json/wp/v2/posts?tags=2656"}, {"href": "https://estreetshuffle.com/index.php/wp-json/wp/v2/pages?tags=2656"}, {"href": "https://estreetshuffle.com/index.php/wp-json/wp/v2/jetpack-portfolio?tags=2656"}], "curies": [{"name": "wp", "href": "https://api.w.org/{rel}", "templated": true}]}}, {"id": 1241, "count": 1, "description": "", "link": "https://estreetshuffle.com/index.php/tag/mark-rivera/", "name": "Mark Rivera", "slug": "mark-rivera", "taxonomy": "post_tag", "meta": [], "_links": {"self": [{"href": "https://estreetshuffle.com/index.php/wp-json/wp/v2/tags/1241", "targetHints": {"allow": ["GET"]}}], "collection": [{"href": "https://estreetshuffle.com/index.php/wp-json/wp/v2/tags"}], "about": [{"href": "https://estreetshuffle.com/index.php/wp-json/wp/v2/taxonomies/post_tag"}], "wp:post_type": [{"href": "https://estreetshuffle.com/index.php/wp-json/wp/v2/posts?tags=1241"}, {"href": "https://estreetshuffle.com/index.php/wp-json/wp/v2/pages?tags=1241"}, {"href": "https://estreetshuffle.com/index.php/wp-json/wp/v2/jetpack-portfolio?tags=1241"}], "curies": [{"name": "wp", "href": "https://api.w.org/{rel}", "templated": true}]}}, {"id": 3154, "count": 1, "description": "", "link": "https://estreetshuffle.com/index.php/tag/marlon-williams/", "name": "Marlon Williams", "slug": "marlon-williams", "taxonomy": "post_tag", "meta": [], "_links": {"self": [{"href": "https://estreetshuffle.com/index.php/wp-json/wp/v2/tags/3154", "targetHints": {"allow": ["GET"]}}], "collection": [{"href": "https://estreetshuffle.com/index.php/wp-json/wp/v2/tags"}], "about": [{"href": "https://estreetshuffle.com/index.php/wp-json/wp/v2/taxonomies/post_tag"}], "wp:post_type": [{"href": "https://estreetshuffle.com/index.php/wp-json/wp/v2/posts?tags=3154"}, {"href": "https://estreetshuffle.com/index.php/wp-json/wp/v2/pages?tags=3154"}, {"href": "https://estreetshuffle.com/index.php/wp-json/wp/v2/jetpack-portfolio?tags=3154"}], "curies": [{"name": "wp", "href": "https://api.w.org/{rel}", "templated": true}]}}, {"id": 1371, "count": 5, "description": "", "link": "https://estreetshuffle.com/index.php/tag/marshall-crenshaw/", "name": "Marshall Crenshaw", "slug": "marshall-crenshaw", "taxonomy": "post_tag", "meta": [], "_links": {"self": [{"href": "https://estreetshuffle.com/index.php/wp-json/wp/v2/tags/1371", "targetHints": {"allow": ["GET"]}}], "collection": [{"href": "https://estreetshuffle.com/index.php/wp-json/wp/v2/tags"}], "about": [{"href": "https://estreetshuffle.com/index.php/wp-json/wp/v2/taxonomies/post_tag"}], "wp:post_type": [{"href": "https://estreetshuffle.com/index.php/wp-json/wp/v2/posts?tags=1371"}, {"href": "https://estreetshuffle.com/index.php/wp-json/wp/v2/pages?tags=1371"}, {"href": "https://estreetshuffle.com/index.php/wp-json/wp/v2/jetpack-portfolio?tags=1371"}], "curies": [{"name": "wp", "href": "https://api.w.org/{rel}", "templated": true}]}}, {"id": 2652, "count": 2, "description": "", "link": "https://estreetshuffle.com/index.php/tag/martha-and-the-vandellas/", "name": "Martha and The Vandellas", "slug": "martha-and-the-vandellas", "taxonomy": "post_tag", "meta": [], "_links": {"self": [{"href": "https://estreetshuffle.com/index.php/wp-json/wp/v2/tags/2652", "targetHints": {"allow": ["GET"]}}], "collection": [{"href": "https://estreetshuffle.com/index.php/wp-json/wp/v2/tags"}], "about": [{"href": "https://estreetshuffle.com/index.php/wp-json/wp/v2/taxonomies/post_tag"}], "wp:post_type": [{"href": "https://estreetshuffle.com/index.php/wp-json/wp/v2/posts?tags=2652"}, {"href": "https://estreetshuffle.com/index.php/wp-json/wp/v2/pages?tags=2652"}, {"href": "https://estreetshuffle.com/index.php/wp-json/wp/v2/jetpack-portfolio?tags=2652"}], "curies": [{"name": "wp", "href": "https://api.w.org/{rel}", "templated": true}]}}, {"id": 1594, "count": 2, "description": "", "link": "https://estreetshuffle.com/index.php/tag/martha-reeves/", "name": "Martha Reeves", "slug": "martha-reeves", "taxonomy": "post_tag", "meta": [], "_links": {"self": [{"href": "https://estreetshuffle.com/index.php/wp-json/wp/v2/tags/1594", "targetHints": {"allow": ["GET"]}}], "collection": [{"href": "https://estreetshuffle.com/index.php/wp-json/wp/v2/tags"}], "about": [{"href": "https://estreetshuffle.com/index.php/wp-json/wp/v2/taxonomies/post_tag"}], "wp:post_type": [{"href": "https://estreetshuffle.com/index.php/wp-json/wp/v2/posts?tags=1594"}, {"href": "https://estreetshuffle.com/index.php/wp-json/wp/v2/pages?tags=1594"}, {"href": "https://estreetshuffle.com/index.php/wp-json/wp/v2/jetpack-portfolio?tags=1594"}], "curies": [{"name": "wp", "href": "https://api.w.org/{rel}", "templated": true}]}}, {"id": 3245, "count": 2, "description": "", "link": "https://estreetshuffle.com/index.php/tag/martin-ekman/", "name": "Martin Ekman", "slug": "martin-ekman", "taxonomy": "post_tag", "meta": [], "_links": {"self": [{"href": "https://estreetshuffle.com/index.php/wp-json/wp/v2/tags/3245", "targetHints": {"allow": ["GET"]}}], "collection": [{"href": "https://estreetshuffle.com/index.php/wp-json/wp/v2/tags"}], "about": [{"href": "https://estreetshuffle.com/index.php/wp-json/wp/v2/taxonomies/post_tag"}], "wp:post_type": [{"href": "https://estreetshuffle.com/index.php/wp-json/wp/v2/posts?tags=3245"}, {"href": "https://estreetshuffle.com/index.php/wp-json/wp/v2/pages?tags=3245"}, {"href": "https://estreetshuffle.com/index.php/wp-json/wp/v2/jetpack-portfolio?tags=3245"}], "curies": [{"name": "wp", "href": "https://api.w.org/{rel}", "templated": true}]}}, {"id": 2283, "count": 1, "description": "", "link": "https://estreetshuffle.com/index.php/tag/martin-luther-king/", "name": "Martin Luther King", "slug": "martin-luther-king", "taxonomy": "post_tag", "meta": [], "_links": {"self": [{"href": "https://estreetshuffle.com/index.php/wp-json/wp/v2/tags/2283", "targetHints": {"allow": ["GET"]}}], "collection": [{"href": "https://estreetshuffle.com/index.php/wp-json/wp/v2/tags"}], "about": [{"href": "https://estreetshuffle.com/index.php/wp-json/wp/v2/taxonomies/post_tag"}], "wp:post_type": [{"href": "https://estreetshuffle.com/index.php/wp-json/wp/v2/posts?tags=2283"}, {"href": "https://estreetshuffle.com/index.php/wp-json/wp/v2/pages?tags=2283"}, {"href": "https://estreetshuffle.com/index.php/wp-json/wp/v2/jetpack-portfolio?tags=2283"}], "curies": [{"name": "wp", "href": "https://api.w.org/{rel}", "templated": true}]}}, {"id": 2743, "count": 1, "description": "", "link": "https://estreetshuffle.com/index.php/tag/martin-scorsese/", "name": "Martin Scorsese", "slug": "martin-scorsese", "taxonomy": "post_tag", "meta": [], "_links": {"self": [{"href": "https://estreetshuffle.com/index.php/wp-json/wp/v2/tags/2743", "targetHints": {"allow": ["GET"]}}], "collection": [{"href": "https://estreetshuffle.com/index.php/wp-json/wp/v2/tags"}], "about": [{"href": "https://estreetshuffle.com/index.php/wp-json/wp/v2/taxonomies/post_tag"}], "wp:post_type": [{"href": "https://estreetshuffle.com/index.php/wp-json/wp/v2/posts?tags=2743"}, {"href": "https://estreetshuffle.com/index.php/wp-json/wp/v2/pages?tags=2743"}, {"href": "https://estreetshuffle.com/index.php/wp-json/wp/v2/jetpack-portfolio?tags=2743"}], "curies": [{"name": "wp", "href": "https://api.w.org/{rel}", "templated": true}]}}, {"id": 382, "count": 1, "description": "", "link": "https://estreetshuffle.com/index.php/tag/martina-linn/", "name": "Martina Linn", "slug": "martina-linn", "taxonomy": "post_tag", "meta": [], "_links": {"self": [{"href": "https://estreetshuffle.com/index.php/wp-json/wp/v2/tags/382", "targetHints": {"allow": ["GET"]}}], "collection": [{"href": "https://estreetshuffle.com/index.php/wp-json/wp/v2/tags"}], "about": [{"href": "https://estreetshuffle.com/index.php/wp-json/wp/v2/taxonomies/post_tag"}], "wp:post_type": [{"href": "https://estreetshuffle.com/index.php/wp-json/wp/v2/posts?tags=382"}, {"href": "https://estreetshuffle.com/index.php/wp-json/wp/v2/pages?tags=382"}, {"href": "https://estreetshuffle.com/index.php/wp-json/wp/v2/jetpack-portfolio?tags=382"}], "curies": [{"name": "wp", "href": "https://api.w.org/{rel}", "templated": true}]}}, {"id": 2288, "count": 1, "description": "", "link": "https://estreetshuffle.com/index.php/tag/marty-rifkin/", "name": "Marty Rifkin", "slug": "marty-rifkin", "taxonomy": "post_tag", "meta": [], "_links": {"self": [{"href": "https://estreetshuffle.com/index.php/wp-json/wp/v2/tags/2288", "targetHints": {"allow": ["GET"]}}], "collection": [{"href": "https://estreetshuffle.com/index.php/wp-json/wp/v2/tags"}], "about": [{"href": "https://estreetshuffle.com/index.php/wp-json/wp/v2/taxonomies/post_tag"}], "wp:post_type": [{"href": "https://estreetshuffle.com/index.php/wp-json/wp/v2/posts?tags=2288"}, {"href": "https://estreetshuffle.com/index.php/wp-json/wp/v2/pages?tags=2288"}, {"href": "https://estreetshuffle.com/index.php/wp-json/wp/v2/jetpack-portfolio?tags=2288"}], "curies": [{"name": "wp", "href": "https://api.w.org/{rel}", "templated": true}]}}, {"id": 2437, "count": 3, "description": "", "link": "https://estreetshuffle.com/index.php/tag/marvin-gaye/", "name": "Marvin Gaye", "slug": "marvin-gaye", "taxonomy": "post_tag", "meta": [], "_links": {"self": [{"href": "https://estreetshuffle.com/index.php/wp-json/wp/v2/tags/2437", "targetHints": {"allow": ["GET"]}}], "collection": [{"href": "https://estreetshuffle.com/index.php/wp-json/wp/v2/tags"}], "about": [{"href": "https://estreetshuffle.com/index.php/wp-json/wp/v2/taxonomies/post_tag"}], "wp:post_type": [{"href": "https://estreetshuffle.com/index.php/wp-json/wp/v2/posts?tags=2437"}, {"href": "https://estreetshuffle.com/index.php/wp-json/wp/v2/pages?tags=2437"}, {"href": "https://estreetshuffle.com/index.php/wp-json/wp/v2/jetpack-portfolio?tags=2437"}], "curies": [{"name": "wp", "href": "https://api.w.org/{rel}", "templated": true}]}}, {"id": 1515, "count": 1, "description": "", "link": "https://estreetshuffle.com/index.php/tag/mary-chapin-carpenter/", "name": "Mary Chapin Carpenter", "slug": "mary-chapin-carpenter", "taxonomy": "post_tag", "meta": [], "_links": {"self": [{"href": "https://estreetshuffle.com/index.php/wp-json/wp/v2/tags/1515", "targetHints": {"allow": ["GET"]}}], "collection": [{"href": "https://estreetshuffle.com/index.php/wp-json/wp/v2/tags"}], "about": [{"href": "https://estreetshuffle.com/index.php/wp-json/wp/v2/taxonomies/post_tag"}], "wp:post_type": [{"href": "https://estreetshuffle.com/index.php/wp-json/wp/v2/posts?tags=1515"}, {"href": "https://estreetshuffle.com/index.php/wp-json/wp/v2/pages?tags=1515"}, {"href": "https://estreetshuffle.com/index.php/wp-json/wp/v2/jetpack-portfolio?tags=1515"}], "curies": [{"name": "wp", "href": "https://api.w.org/{rel}", "templated": true}]}}, {"id": 2305, "count": 1, "description": "", "link": "https://estreetshuffle.com/index.php/tag/mary-cutrufello/", "name": "Mary Cutrufello", "slug": "mary-cutrufello", "taxonomy": "post_tag", "meta": [], "_links": {"self": [{"href": "https://estreetshuffle.com/index.php/wp-json/wp/v2/tags/2305", "targetHints": {"allow": ["GET"]}}], "collection": [{"href": "https://estreetshuffle.com/index.php/wp-json/wp/v2/tags"}], "about": [{"href": "https://estreetshuffle.com/index.php/wp-json/wp/v2/taxonomies/post_tag"}], "wp:post_type": [{"href": "https://estreetshuffle.com/index.php/wp-json/wp/v2/posts?tags=2305"}, {"href": "https://estreetshuffle.com/index.php/wp-json/wp/v2/pages?tags=2305"}, {"href": "https://estreetshuffle.com/index.php/wp-json/wp/v2/jetpack-portfolio?tags=2305"}], "curies": [{"name": "wp", "href": "https://api.w.org/{rel}", "templated": true}]}}, {"id": 3020, "count": 1, "description": "", "link": "https://estreetshuffle.com/index.php/tag/mary-g/", "name": "Mary G", "slug": "mary-g", "taxonomy": "post_tag", "meta": [], "_links": {"self": [{"href": "https://estreetshuffle.com/index.php/wp-json/wp/v2/tags/3020", "targetHints": {"allow": ["GET"]}}], "collection": [{"href": "https://estreetshuffle.com/index.php/wp-json/wp/v2/tags"}], "about": [{"href": "https://estreetshuffle.com/index.php/wp-json/wp/v2/taxonomies/post_tag"}], "wp:post_type": [{"href": "https://estreetshuffle.com/index.php/wp-json/wp/v2/posts?tags=3020"}, {"href": "https://estreetshuffle.com/index.php/wp-json/wp/v2/pages?tags=3020"}, {"href": "https://estreetshuffle.com/index.php/wp-json/wp/v2/jetpack-portfolio?tags=3020"}], "curies": [{"name": "wp", "href": "https://api.w.org/{rel}", "templated": true}]}}, {"id": 2292, "count": 1, "description": "", "link": "https://estreetshuffle.com/index.php/tag/mary-j-blige/", "name": "Mary J. Blige", "slug": "mary-j-blige", "taxonomy": "post_tag", "meta": [], "_links": {"self": [{"href": "https://estreetshuffle.com/index.php/wp-json/wp/v2/tags/2292", "targetHints": {"allow": ["GET"]}}], "collection": [{"href": "https://estreetshuffle.com/index.php/wp-json/wp/v2/tags"}], "about": [{"href": "https://estreetshuffle.com/index.php/wp-json/wp/v2/taxonomies/post_tag"}], "wp:post_type": [{"href": "https://estreetshuffle.com/index.php/wp-json/wp/v2/posts?tags=2292"}, {"href": "https://estreetshuffle.com/index.php/wp-json/wp/v2/pages?tags=2292"}, {"href": "https://estreetshuffle.com/index.php/wp-json/wp/v2/jetpack-portfolio?tags=2292"}], "curies": [{"name": "wp", "href": "https://api.w.org/{rel}", "templated": true}]}}, {"id": 2291, "count": 1, "description": "", "link": "https://estreetshuffle.com/index.php/tag/mary-lou/", "name": "Mary Lou", "slug": "mary-lou", "taxonomy": "post_tag", "meta": [], "_links": {"self": [{"href": "https://estreetshuffle.com/index.php/wp-json/wp/v2/tags/2291", "targetHints": {"allow": ["GET"]}}], "collection": [{"href": "https://estreetshuffle.com/index.php/wp-json/wp/v2/tags"}], "about": [{"href": "https://estreetshuffle.com/index.php/wp-json/wp/v2/taxonomies/post_tag"}], "wp:post_type": [{"href": "https://estreetshuffle.com/index.php/wp-json/wp/v2/posts?tags=2291"}, {"href": "https://estreetshuffle.com/index.php/wp-json/wp/v2/pages?tags=2291"}, {"href": "https://estreetshuffle.com/index.php/wp-json/wp/v2/jetpack-portfolio?tags=2291"}], "curies": [{"name": "wp", "href": "https://api.w.org/{rel}", "templated": true}]}}, {"id": 1996, "count": 1, "description": "", "link": "https://estreetshuffle.com/index.php/tag/mary-louis-watson/", "name": "Mary Louis Watson", "slug": "mary-louis-watson", "taxonomy": "post_tag", "meta": [], "_links": {"self": [{"href": "https://estreetshuffle.com/index.php/wp-json/wp/v2/tags/1996", "targetHints": {"allow": ["GET"]}}], "collection": [{"href": "https://estreetshuffle.com/index.php/wp-json/wp/v2/tags"}], "about": [{"href": "https://estreetshuffle.com/index.php/wp-json/wp/v2/taxonomies/post_tag"}], "wp:post_type": [{"href": "https://estreetshuffle.com/index.php/wp-json/wp/v2/posts?tags=1996"}, {"href": "https://estreetshuffle.com/index.php/wp-json/wp/v2/pages?tags=1996"}, {"href": "https://estreetshuffle.com/index.php/wp-json/wp/v2/jetpack-portfolio?tags=1996"}], "curies": [{"name": "wp", "href": "https://api.w.org/{rel}", "templated": true}]}}, {"id": 1705, "count": 1, "description": "", "link": "https://estreetshuffle.com/index.php/tag/mary-louise-watson/", "name": "Mary Louise Watson", "slug": "mary-louise-watson", "taxonomy": "post_tag", "meta": [], "_links": {"self": [{"href": "https://estreetshuffle.com/index.php/wp-json/wp/v2/tags/1705", "targetHints": {"allow": ["GET"]}}], "collection": [{"href": "https://estreetshuffle.com/index.php/wp-json/wp/v2/tags"}], "about": [{"href": "https://estreetshuffle.com/index.php/wp-json/wp/v2/taxonomies/post_tag"}], "wp:post_type": [{"href": "https://estreetshuffle.com/index.php/wp-json/wp/v2/posts?tags=1705"}, {"href": "https://estreetshuffle.com/index.php/wp-json/wp/v2/pages?tags=1705"}, {"href": "https://estreetshuffle.com/index.php/wp-json/wp/v2/jetpack-portfolio?tags=1705"}], "curies": [{"name": "wp", "href": "https://api.w.org/{rel}", "templated": true}]}}, {"id": 654, "count": 1, "description": "", "link": "https://estreetshuffle.com/index.php/tag/mary-mary/", "name": "Mary Mary", "slug": "mary-mary", "taxonomy": "post_tag", "meta": [], "_links": {"self": [{"href": "https://estreetshuffle.com/index.php/wp-json/wp/v2/tags/654", "targetHints": {"allow": ["GET"]}}], "collection": [{"href": "https://estreetshuffle.com/index.php/wp-json/wp/v2/tags"}], "about": [{"href": "https://estreetshuffle.com/index.php/wp-json/wp/v2/taxonomies/post_tag"}], "wp:post_type": [{"href": "https://estreetshuffle.com/index.php/wp-json/wp/v2/posts?tags=654"}, {"href": "https://estreetshuffle.com/index.php/wp-json/wp/v2/pages?tags=654"}, {"href": "https://estreetshuffle.com/index.php/wp-json/wp/v2/jetpack-portfolio?tags=654"}], "curies": [{"name": "wp", "href": "https://api.w.org/{rel}", "templated": true}]}}, {"id": 845, "count": 3, "description": "", "link": "https://estreetshuffle.com/index.php/tag/mary-queen-of-arkansas/", "name": "Mary Queen of Arkansas", "slug": "mary-queen-of-arkansas", "taxonomy": "post_tag", "meta": [], "_links": {"self": [{"href": "https://estreetshuffle.com/index.php/wp-json/wp/v2/tags/845", "targetHints": {"allow": ["GET"]}}], "collection": [{"href": "https://estreetshuffle.com/index.php/wp-json/wp/v2/tags"}], "about": [{"href": "https://estreetshuffle.com/index.php/wp-json/wp/v2/taxonomies/post_tag"}], "wp:post_type": [{"href": "https://estreetshuffle.com/index.php/wp-json/wp/v2/posts?tags=845"}, {"href": "https://estreetshuffle.com/index.php/wp-json/wp/v2/pages?tags=845"}, {"href": "https://estreetshuffle.com/index.php/wp-json/wp/v2/jetpack-portfolio?tags=845"}], "curies": [{"name": "wp", "href": "https://api.w.org/{rel}", "templated": true}]}}, {"id": 1233, "count": 1, "description": "", "link": "https://estreetshuffle.com/index.php/tag/mary-turner/", "name": "Mary Turner", "slug": "mary-turner", "taxonomy": "post_tag", "meta": [], "_links": {"self": [{"href": "https://estreetshuffle.com/index.php/wp-json/wp/v2/tags/1233", "targetHints": {"allow": ["GET"]}}], "collection": [{"href": "https://estreetshuffle.com/index.php/wp-json/wp/v2/tags"}], "about": [{"href": "https://estreetshuffle.com/index.php/wp-json/wp/v2/taxonomies/post_tag"}], "wp:post_type": [{"href": "https://estreetshuffle.com/index.php/wp-json/wp/v2/posts?tags=1233"}, {"href": "https://estreetshuffle.com/index.php/wp-json/wp/v2/pages?tags=1233"}, {"href": "https://estreetshuffle.com/index.php/wp-json/wp/v2/jetpack-portfolio?tags=1233"}], "curies": [{"name": "wp", "href": "https://api.w.org/{rel}", "templated": true}]}}, {"id": 3444, "count": 1, "description": "", "link": "https://estreetshuffle.com/index.php/tag/marys-place/", "name": "Mary's Place", "slug": "marys-place", "taxonomy": "post_tag", "meta": [], "_links": {"self": [{"href": "https://estreetshuffle.com/index.php/wp-json/wp/v2/tags/3444", "targetHints": {"allow": ["GET"]}}], "collection": [{"href": "https://estreetshuffle.com/index.php/wp-json/wp/v2/tags"}], "about": [{"href": "https://estreetshuffle.com/index.php/wp-json/wp/v2/taxonomies/post_tag"}], "wp:post_type": [{"href": "https://estreetshuffle.com/index.php/wp-json/wp/v2/posts?tags=3444"}, {"href": "https://estreetshuffle.com/index.php/wp-json/wp/v2/pages?tags=3444"}, {"href": "https://estreetshuffle.com/index.php/wp-json/wp/v2/jetpack-portfolio?tags=3444"}], "curies": [{"name": "wp", "href": "https://api.w.org/{rel}", "templated": true}]}}, {"id": 318, "count": 1, "description": "", "link": "https://estreetshuffle.com/index.php/tag/mat-kearney/", "name": "Mat Kearney", "slug": "mat-kearney", "taxonomy": "post_tag", "meta": [], "_links": {"self": [{"href": "https://estreetshuffle.com/index.php/wp-json/wp/v2/tags/318", "targetHints": {"allow": ["GET"]}}], "collection": [{"href": "https://estreetshuffle.com/index.php/wp-json/wp/v2/tags"}], "about": [{"href": "https://estreetshuffle.com/index.php/wp-json/wp/v2/taxonomies/post_tag"}], "wp:post_type": [{"href": "https://estreetshuffle.com/index.php/wp-json/wp/v2/posts?tags=318"}, {"href": "https://estreetshuffle.com/index.php/wp-json/wp/v2/pages?tags=318"}, {"href": "https://estreetshuffle.com/index.php/wp-json/wp/v2/jetpack-portfolio?tags=318"}], "curies": [{"name": "wp", "href": "https://api.w.org/{rel}", "templated": true}]}}, {"id": 1329, "count": 1, "description": "", "link": "https://estreetshuffle.com/index.php/tag/mat-lauer/", "name": "Mat Lauer", "slug": "mat-lauer", "taxonomy": "post_tag", "meta": [], "_links": {"self": [{"href": "https://estreetshuffle.com/index.php/wp-json/wp/v2/tags/1329", "targetHints": {"allow": ["GET"]}}], "collection": [{"href": "https://estreetshuffle.com/index.php/wp-json/wp/v2/tags"}], "about": [{"href": "https://estreetshuffle.com/index.php/wp-json/wp/v2/taxonomies/post_tag"}], "wp:post_type": [{"href": "https://estreetshuffle.com/index.php/wp-json/wp/v2/posts?tags=1329"}, {"href": "https://estreetshuffle.com/index.php/wp-json/wp/v2/pages?tags=1329"}, {"href": "https://estreetshuffle.com/index.php/wp-json/wp/v2/jetpack-portfolio?tags=1329"}], "curies": [{"name": "wp", "href": "https://api.w.org/{rel}", "templated": true}]}}, {"id": 1456, "count": 1, "description": "", "link": "https://estreetshuffle.com/index.php/tag/matamoras-banks/", "name": "Matamoras Banks", "slug": "matamoras-banks", "taxonomy": "post_tag", "meta": [], "_links": {"self": [{"href": "https://estreetshuffle.com/index.php/wp-json/wp/v2/tags/1456", "targetHints": {"allow": ["GET"]}}], "collection": [{"href": "https://estreetshuffle.com/index.php/wp-json/wp/v2/tags"}], "about": [{"href": "https://estreetshuffle.com/index.php/wp-json/wp/v2/taxonomies/post_tag"}], "wp:post_type": [{"href": "https://estreetshuffle.com/index.php/wp-json/wp/v2/posts?tags=1456"}, {"href": "https://estreetshuffle.com/index.php/wp-json/wp/v2/pages?tags=1456"}, {"href": "https://estreetshuffle.com/index.php/wp-json/wp/v2/jetpack-portfolio?tags=1456"}], "curies": [{"name": "wp", "href": "https://api.w.org/{rel}", "templated": true}]}}, {"id": 2520, "count": 1, "description": "", "link": "https://estreetshuffle.com/index.php/tag/matamoros-banks/", "name": "Matamoros Banks", "slug": "matamoros-banks", "taxonomy": "post_tag", "meta": [], "_links": {"self": [{"href": "https://estreetshuffle.com/index.php/wp-json/wp/v2/tags/2520", "targetHints": {"allow": ["GET"]}}], "collection": [{"href": "https://estreetshuffle.com/index.php/wp-json/wp/v2/tags"}], "about": [{"href": "https://estreetshuffle.com/index.php/wp-json/wp/v2/taxonomies/post_tag"}], "wp:post_type": [{"href": "https://estreetshuffle.com/index.php/wp-json/wp/v2/posts?tags=2520"}, {"href": "https://estreetshuffle.com/index.php/wp-json/wp/v2/pages?tags=2520"}, {"href": "https://estreetshuffle.com/index.php/wp-json/wp/v2/jetpack-portfolio?tags=2520"}], "curies": [{"name": "wp", "href": "https://api.w.org/{rel}", "templated": true}]}}, {"id": 44, "count": 1, "description": "", "link": "https://estreetshuffle.com/index.php/tag/matrix/", "name": "Matrix", "slug": "matrix", "taxonomy": "post_tag", "meta": [], "_links": {"self": [{"href": "https://estreetshuffle.com/index.php/wp-json/wp/v2/tags/44", "targetHints": {"allow": ["GET"]}}], "collection": [{"href": "https://estreetshuffle.com/index.php/wp-json/wp/v2/tags"}], "about": [{"href": "https://estreetshuffle.com/index.php/wp-json/wp/v2/taxonomies/post_tag"}], "wp:post_type": [{"href": "https://estreetshuffle.com/index.php/wp-json/wp/v2/posts?tags=44"}, {"href": "https://estreetshuffle.com/index.php/wp-json/wp/v2/pages?tags=44"}, {"href": "https://estreetshuffle.com/index.php/wp-json/wp/v2/jetpack-portfolio?tags=44"}], "curies": [{"name": "wp", "href": "https://api.w.org/{rel}", "templated": true}]}}, {"id": 462, "count": 1, "description": "", "link": "https://estreetshuffle.com/index.php/tag/matt-nathanson/", "name": "Matt Nathanson", "slug": "matt-nathanson", "taxonomy": "post_tag", "meta": [], "_links": {"self": [{"href": "https://estreetshuffle.com/index.php/wp-json/wp/v2/tags/462", "targetHints": {"allow": ["GET"]}}], "collection": [{"href": "https://estreetshuffle.com/index.php/wp-json/wp/v2/tags"}], "about": [{"href": "https://estreetshuffle.com/index.php/wp-json/wp/v2/taxonomies/post_tag"}], "wp:post_type": [{"href": "https://estreetshuffle.com/index.php/wp-json/wp/v2/posts?tags=462"}, {"href": "https://estreetshuffle.com/index.php/wp-json/wp/v2/pages?tags=462"}, {"href": "https://estreetshuffle.com/index.php/wp-json/wp/v2/jetpack-portfolio?tags=462"}], "curies": [{"name": "wp", "href": "https://api.w.org/{rel}", "templated": true}]}}, {"id": 3328, "count": 1, "description": "", "link": "https://estreetshuffle.com/index.php/tag/matt-oree-band/", "name": "Matt O'Ree Band", "slug": "matt-oree-band", "taxonomy": "post_tag", "meta": [], "_links": {"self": [{"href": "https://estreetshuffle.com/index.php/wp-json/wp/v2/tags/3328", "targetHints": {"allow": ["GET"]}}], "collection": [{"href": "https://estreetshuffle.com/index.php/wp-json/wp/v2/tags"}], "about": [{"href": "https://estreetshuffle.com/index.php/wp-json/wp/v2/taxonomies/post_tag"}], "wp:post_type": [{"href": "https://estreetshuffle.com/index.php/wp-json/wp/v2/posts?tags=3328"}, {"href": "https://estreetshuffle.com/index.php/wp-json/wp/v2/pages?tags=3328"}, {"href": "https://estreetshuffle.com/index.php/wp-json/wp/v2/jetpack-portfolio?tags=3328"}], "curies": [{"name": "wp", "href": "https://api.w.org/{rel}", "templated": true}]}}, {"id": 1358, "count": 1, "description": "", "link": "https://estreetshuffle.com/index.php/tag/maurice-williams/", "name": "Maurice Williams", "slug": "maurice-williams", "taxonomy": "post_tag", "meta": [], "_links": {"self": [{"href": "https://estreetshuffle.com/index.php/wp-json/wp/v2/tags/1358", "targetHints": {"allow": ["GET"]}}], "collection": [{"href": "https://estreetshuffle.com/index.php/wp-json/wp/v2/tags"}], "about": [{"href": "https://estreetshuffle.com/index.php/wp-json/wp/v2/taxonomies/post_tag"}], "wp:post_type": [{"href": "https://estreetshuffle.com/index.php/wp-json/wp/v2/posts?tags=1358"}, {"href": "https://estreetshuffle.com/index.php/wp-json/wp/v2/pages?tags=1358"}, {"href": "https://estreetshuffle.com/index.php/wp-json/wp/v2/jetpack-portfolio?tags=1358"}], "curies": [{"name": "wp", "href": "https://api.w.org/{rel}", "templated": true}]}}, {"id": 632, "count": 18, "description": "", "link": "https://estreetshuffle.com/index.php/tag/max-weinberg/", "name": "Max Weinberg", "slug": "max-weinberg", "taxonomy": "post_tag", "meta": [], "_links": {"self": [{"href": "https://estreetshuffle.com/index.php/wp-json/wp/v2/tags/632", "targetHints": {"allow": ["GET"]}}], "collection": [{"href": "https://estreetshuffle.com/index.php/wp-json/wp/v2/tags"}], "about": [{"href": "https://estreetshuffle.com/index.php/wp-json/wp/v2/taxonomies/post_tag"}], "wp:post_type": [{"href": "https://estreetshuffle.com/index.php/wp-json/wp/v2/posts?tags=632"}, {"href": "https://estreetshuffle.com/index.php/wp-json/wp/v2/pages?tags=632"}, {"href": "https://estreetshuffle.com/index.php/wp-json/wp/v2/jetpack-portfolio?tags=632"}], "curies": [{"name": "wp", "href": "https://api.w.org/{rel}", "templated": true}]}}, {"id": 809, "count": 14, "description": "", "link": "https://estreetshuffle.com/index.php/tag/max-weinberg-7/", "name": "Max Weinberg 7", "slug": "max-weinberg-7", "taxonomy": "post_tag", "meta": [], "_links": {"self": [{"href": "https://estreetshuffle.com/index.php/wp-json/wp/v2/tags/809", "targetHints": {"allow": ["GET"]}}], "collection": [{"href": "https://estreetshuffle.com/index.php/wp-json/wp/v2/tags"}], "about": [{"href": "https://estreetshuffle.com/index.php/wp-json/wp/v2/taxonomies/post_tag"}], "wp:post_type": [{"href": "https://estreetshuffle.com/index.php/wp-json/wp/v2/posts?tags=809"}, {"href": "https://estreetshuffle.com/index.php/wp-json/wp/v2/pages?tags=809"}, {"href": "https://estreetshuffle.com/index.php/wp-json/wp/v2/jetpack-portfolio?tags=809"}], "curies": [{"name": "wp", "href": "https://api.w.org/{rel}", "templated": true}]}}, {"id": 173, "count": 25, "description": "", "link": "https://estreetshuffle.com/index.php/tag/maxs-kansas-city/", "name": "Max's Kansas City", "slug": "maxs-kansas-city", "taxonomy": "post_tag", "meta": [], "_links": {"self": [{"href": "https://estreetshuffle.com/index.php/wp-json/wp/v2/tags/173", "targetHints": {"allow": ["GET"]}}], "collection": [{"href": "https://estreetshuffle.com/index.php/wp-json/wp/v2/tags"}], "about": [{"href": "https://estreetshuffle.com/index.php/wp-json/wp/v2/taxonomies/post_tag"}], "wp:post_type": [{"href": "https://estreetshuffle.com/index.php/wp-json/wp/v2/posts?tags=173"}, {"href": "https://estreetshuffle.com/index.php/wp-json/wp/v2/pages?tags=173"}, {"href": "https://estreetshuffle.com/index.php/wp-json/wp/v2/jetpack-portfolio?tags=173"}], "curies": [{"name": "wp", "href": "https://api.w.org/{rel}", "templated": true}]}}, {"id": 673, "count": 2, "description": "", "link": "https://estreetshuffle.com/index.php/tag/may-i/", "name": "May I", "slug": "may-i", "taxonomy": "post_tag", "meta": [], "_links": {"self": [{"href": "https://estreetshuffle.com/index.php/wp-json/wp/v2/tags/673", "targetHints": {"allow": ["GET"]}}], "collection": [{"href": "https://estreetshuffle.com/index.php/wp-json/wp/v2/tags"}], "about": [{"href": "https://estreetshuffle.com/index.php/wp-json/wp/v2/taxonomies/post_tag"}], "wp:post_type": [{"href": "https://estreetshuffle.com/index.php/wp-json/wp/v2/posts?tags=673"}, {"href": "https://estreetshuffle.com/index.php/wp-json/wp/v2/pages?tags=673"}, {"href": "https://estreetshuffle.com/index.php/wp-json/wp/v2/jetpack-portfolio?tags=673"}], "curies": [{"name": "wp", "href": "https://api.w.org/{rel}", "templated": true}]}}, {"id": 2824, "count": 1, "description": "", "link": "https://estreetshuffle.com/index.php/tag/me-and-my-baby-got-our-own-thing-going/", "name": "Me and My Baby Got Our Own Thing Going", "slug": "me-and-my-baby-got-our-own-thing-going", "taxonomy": "post_tag", "meta": [], "_links": {"self": [{"href": "https://estreetshuffle.com/index.php/wp-json/wp/v2/tags/2824", "targetHints": {"allow": ["GET"]}}], "collection": [{"href": "https://estreetshuffle.com/index.php/wp-json/wp/v2/tags"}], "about": [{"href": "https://estreetshuffle.com/index.php/wp-json/wp/v2/taxonomies/post_tag"}], "wp:post_type": [{"href": "https://estreetshuffle.com/index.php/wp-json/wp/v2/posts?tags=2824"}, {"href": "https://estreetshuffle.com/index.php/wp-json/wp/v2/pages?tags=2824"}, {"href": "https://estreetshuffle.com/index.php/wp-json/wp/v2/jetpack-portfolio?tags=2824"}], "curies": [{"name": "wp", "href": "https://api.w.org/{rel}", "templated": true}]}}, {"id": 3059, "count": 1, "description": "", "link": "https://estreetshuffle.com/index.php/tag/meet-me-at-the-end-of-the-world/", "name": "Meet Me at the End of the World", "slug": "meet-me-at-the-end-of-the-world", "taxonomy": "post_tag", "meta": [], "_links": {"self": [{"href": "https://estreetshuffle.com/index.php/wp-json/wp/v2/tags/3059", "targetHints": {"allow": ["GET"]}}], "collection": [{"href": "https://estreetshuffle.com/index.php/wp-json/wp/v2/tags"}], "about": [{"href": "https://estreetshuffle.com/index.php/wp-json/wp/v2/taxonomies/post_tag"}], "wp:post_type": [{"href": "https://estreetshuffle.com/index.php/wp-json/wp/v2/posts?tags=3059"}, {"href": "https://estreetshuffle.com/index.php/wp-json/wp/v2/pages?tags=3059"}, {"href": "https://estreetshuffle.com/index.php/wp-json/wp/v2/jetpack-portfolio?tags=3059"}], "curies": [{"name": "wp", "href": "https://api.w.org/{rel}", "templated": true}]}}, {"id": 319, "count": 10, "description": "", "link": "https://estreetshuffle.com/index.php/tag/meet-me-in-the-city/", "name": "Meet Me in the City", "slug": "meet-me-in-the-city", "taxonomy": "post_tag", "meta": [], "_links": {"self": [{"href": "https://estreetshuffle.com/index.php/wp-json/wp/v2/tags/319", "targetHints": {"allow": ["GET"]}}], "collection": [{"href": "https://estreetshuffle.com/index.php/wp-json/wp/v2/tags"}], "about": [{"href": "https://estreetshuffle.com/index.php/wp-json/wp/v2/taxonomies/post_tag"}], "wp:post_type": [{"href": "https://estreetshuffle.com/index.php/wp-json/wp/v2/posts?tags=319"}, {"href": "https://estreetshuffle.com/index.php/wp-json/wp/v2/pages?tags=319"}, {"href": "https://estreetshuffle.com/index.php/wp-json/wp/v2/jetpack-portfolio?tags=319"}], "curies": [{"name": "wp", "href": "https://api.w.org/{rel}", "templated": true}]}}, {"id": 2296, "count": 1, "description": "", "link": "https://estreetshuffle.com/index.php/tag/meet-the-flintstones/", "name": "Meet the Flintstones", "slug": "meet-the-flintstones", "taxonomy": "post_tag", "meta": [], "_links": {"self": [{"href": "https://estreetshuffle.com/index.php/wp-json/wp/v2/tags/2296", "targetHints": {"allow": ["GET"]}}], "collection": [{"href": "https://estreetshuffle.com/index.php/wp-json/wp/v2/tags"}], "about": [{"href": "https://estreetshuffle.com/index.php/wp-json/wp/v2/taxonomies/post_tag"}], "wp:post_type": [{"href": "https://estreetshuffle.com/index.php/wp-json/wp/v2/posts?tags=2296"}, {"href": "https://estreetshuffle.com/index.php/wp-json/wp/v2/pages?tags=2296"}, {"href": "https://estreetshuffle.com/index.php/wp-json/wp/v2/jetpack-portfolio?tags=2296"}], "curies": [{"name": "wp", "href": "https://api.w.org/{rel}", "templated": true}]}}, {"id": 488, "count": 9, "description": "", "link": "https://estreetshuffle.com/index.php/tag/meeting-across-the-river/", "name": "Meeting Across the River", "slug": "meeting-across-the-river", "taxonomy": "post_tag", "meta": [], "_links": {"self": [{"href": "https://estreetshuffle.com/index.php/wp-json/wp/v2/tags/488", "targetHints": {"allow": ["GET"]}}], "collection": [{"href": "https://estreetshuffle.com/index.php/wp-json/wp/v2/tags"}], "about": [{"href": "https://estreetshuffle.com/index.php/wp-json/wp/v2/taxonomies/post_tag"}], "wp:post_type": [{"href": "https://estreetshuffle.com/index.php/wp-json/wp/v2/posts?tags=488"}, {"href": "https://estreetshuffle.com/index.php/wp-json/wp/v2/pages?tags=488"}, {"href": "https://estreetshuffle.com/index.php/wp-json/wp/v2/jetpack-portfolio?tags=488"}], "curies": [{"name": "wp", "href": "https://api.w.org/{rel}", "templated": true}]}}, {"id": 3295, "count": 1, "description": "", "link": "https://estreetshuffle.com/index.php/tag/megan-oneill/", "name": "Megan O'Neill", "slug": "megan-oneill", "taxonomy": "post_tag", "meta": [], "_links": {"self": [{"href": "https://estreetshuffle.com/index.php/wp-json/wp/v2/tags/3295", "targetHints": {"allow": ["GET"]}}], "collection": [{"href": "https://estreetshuffle.com/index.php/wp-json/wp/v2/tags"}], "about": [{"href": "https://estreetshuffle.com/index.php/wp-json/wp/v2/taxonomies/post_tag"}], "wp:post_type": [{"href": "https://estreetshuffle.com/index.php/wp-json/wp/v2/posts?tags=3295"}, {"href": "https://estreetshuffle.com/index.php/wp-json/wp/v2/pages?tags=3295"}, {"href": "https://estreetshuffle.com/index.php/wp-json/wp/v2/jetpack-portfolio?tags=3295"}], "curies": [{"name": "wp", "href": "https://api.w.org/{rel}", "templated": true}]}}, {"id": 1885, "count": 1, "description": "", "link": "https://estreetshuffle.com/index.php/tag/meiert-avis/", "name": "Meiert Avis", "slug": "meiert-avis", "taxonomy": "post_tag", "meta": [], "_links": {"self": [{"href": "https://estreetshuffle.com/index.php/wp-json/wp/v2/tags/1885", "targetHints": {"allow": ["GET"]}}], "collection": [{"href": "https://estreetshuffle.com/index.php/wp-json/wp/v2/tags"}], "about": [{"href": "https://estreetshuffle.com/index.php/wp-json/wp/v2/taxonomies/post_tag"}], "wp:post_type": [{"href": "https://estreetshuffle.com/index.php/wp-json/wp/v2/posts?tags=1885"}, {"href": "https://estreetshuffle.com/index.php/wp-json/wp/v2/pages?tags=1885"}, {"href": "https://estreetshuffle.com/index.php/wp-json/wp/v2/jetpack-portfolio?tags=1885"}], "curies": [{"name": "wp", "href": "https://api.w.org/{rel}", "templated": true}]}}, {"id": 3222, "count": 1, "description": "", "link": "https://estreetshuffle.com/index.php/tag/mel-mcdaniel/", "name": "Mel McDaniel", "slug": "mel-mcdaniel", "taxonomy": "post_tag", "meta": [], "_links": {"self": [{"href": "https://estreetshuffle.com/index.php/wp-json/wp/v2/tags/3222", "targetHints": {"allow": ["GET"]}}], "collection": [{"href": "https://estreetshuffle.com/index.php/wp-json/wp/v2/tags"}], "about": [{"href": "https://estreetshuffle.com/index.php/wp-json/wp/v2/taxonomies/post_tag"}], "wp:post_type": [{"href": "https://estreetshuffle.com/index.php/wp-json/wp/v2/posts?tags=3222"}, {"href": "https://estreetshuffle.com/index.php/wp-json/wp/v2/pages?tags=3222"}, {"href": "https://estreetshuffle.com/index.php/wp-json/wp/v2/jetpack-portfolio?tags=3222"}], "curies": [{"name": "wp", "href": "https://api.w.org/{rel}", "templated": true}]}}, {"id": 503, "count": 0, "description": "", "link": "https://estreetshuffle.com/index.php/tag/melborune/", "name": "Melborune", "slug": "melborune", "taxonomy": "post_tag", "meta": [], "_links": {"self": [{"href": "https://estreetshuffle.com/index.php/wp-json/wp/v2/tags/503", "targetHints": {"allow": ["GET"]}}], "collection": [{"href": "https://estreetshuffle.com/index.php/wp-json/wp/v2/tags"}], "about": [{"href": "https://estreetshuffle.com/index.php/wp-json/wp/v2/taxonomies/post_tag"}], "wp:post_type": [{"href": "https://estreetshuffle.com/index.php/wp-json/wp/v2/posts?tags=503"}, {"href": "https://estreetshuffle.com/index.php/wp-json/wp/v2/pages?tags=503"}, {"href": "https://estreetshuffle.com/index.php/wp-json/wp/v2/jetpack-portfolio?tags=503"}], "curies": [{"name": "wp", "href": "https://api.w.org/{rel}", "templated": true}]}}, {"id": 202, "count": 11, "description": "", "link": "https://estreetshuffle.com/index.php/tag/melbourne/", "name": "Melbourne", "slug": "melbourne", "taxonomy": "post_tag", "meta": [], "_links": {"self": [{"href": "https://estreetshuffle.com/index.php/wp-json/wp/v2/tags/202", "targetHints": {"allow": ["GET"]}}], "collection": [{"href": "https://estreetshuffle.com/index.php/wp-json/wp/v2/tags"}], "about": [{"href": "https://estreetshuffle.com/index.php/wp-json/wp/v2/taxonomies/post_tag"}], "wp:post_type": [{"href": "https://estreetshuffle.com/index.php/wp-json/wp/v2/posts?tags=202"}, {"href": "https://estreetshuffle.com/index.php/wp-json/wp/v2/pages?tags=202"}, {"href": "https://estreetshuffle.com/index.php/wp-json/wp/v2/jetpack-portfolio?tags=202"}], "curies": [{"name": "wp", "href": "https://api.w.org/{rel}", "templated": true}]}}, {"id": 296, "count": 4, "description": "", "link": "https://estreetshuffle.com/index.php/tag/melissa-etheridge/", "name": "Melissa Etheridge", "slug": "melissa-etheridge", "taxonomy": "post_tag", "meta": [], "_links": {"self": [{"href": "https://estreetshuffle.com/index.php/wp-json/wp/v2/tags/296", "targetHints": {"allow": ["GET"]}}], "collection": [{"href": "https://estreetshuffle.com/index.php/wp-json/wp/v2/tags"}], "about": [{"href": "https://estreetshuffle.com/index.php/wp-json/wp/v2/taxonomies/post_tag"}], "wp:post_type": [{"href": "https://estreetshuffle.com/index.php/wp-json/wp/v2/posts?tags=296"}, {"href": "https://estreetshuffle.com/index.php/wp-json/wp/v2/pages?tags=296"}, {"href": "https://estreetshuffle.com/index.php/wp-json/wp/v2/jetpack-portfolio?tags=296"}], "curies": [{"name": "wp", "href": "https://api.w.org/{rel}", "templated": true}]}}, {"id": 2883, "count": 1, "description": "", "link": "https://estreetshuffle.com/index.php/tag/melissa-mcclelland/", "name": "Melissa McClelland", "slug": "melissa-mcclelland", "taxonomy": "post_tag", "meta": [], "_links": {"self": [{"href": "https://estreetshuffle.com/index.php/wp-json/wp/v2/tags/2883", "targetHints": {"allow": ["GET"]}}], "collection": [{"href": "https://estreetshuffle.com/index.php/wp-json/wp/v2/tags"}], "about": [{"href": "https://estreetshuffle.com/index.php/wp-json/wp/v2/taxonomies/post_tag"}], "wp:post_type": [{"href": "https://estreetshuffle.com/index.php/wp-json/wp/v2/posts?tags=2883"}, {"href": "https://estreetshuffle.com/index.php/wp-json/wp/v2/pages?tags=2883"}, {"href": "https://estreetshuffle.com/index.php/wp-json/wp/v2/jetpack-portfolio?tags=2883"}], "curies": [{"name": "wp", "href": "https://api.w.org/{rel}", "templated": true}]}}, {"id": 1989, "count": 1, "description": "", "link": "https://estreetshuffle.com/index.php/tag/memphia/", "name": "Memphia", "slug": "memphia", "taxonomy": "post_tag", "meta": [], "_links": {"self": [{"href": "https://estreetshuffle.com/index.php/wp-json/wp/v2/tags/1989", "targetHints": {"allow": ["GET"]}}], "collection": [{"href": "https://estreetshuffle.com/index.php/wp-json/wp/v2/tags"}], "about": [{"href": "https://estreetshuffle.com/index.php/wp-json/wp/v2/taxonomies/post_tag"}], "wp:post_type": [{"href": "https://estreetshuffle.com/index.php/wp-json/wp/v2/posts?tags=1989"}, {"href": "https://estreetshuffle.com/index.php/wp-json/wp/v2/pages?tags=1989"}, {"href": "https://estreetshuffle.com/index.php/wp-json/wp/v2/jetpack-portfolio?tags=1989"}], "curies": [{"name": "wp", "href": "https://api.w.org/{rel}", "templated": true}]}}, {"id": 357, "count": 6, "description": "", "link": "https://estreetshuffle.com/index.php/tag/memphis/", "name": "Memphis", "slug": "memphis", "taxonomy": "post_tag", "meta": [], "_links": {"self": [{"href": "https://estreetshuffle.com/index.php/wp-json/wp/v2/tags/357", "targetHints": {"allow": ["GET"]}}], "collection": [{"href": "https://estreetshuffle.com/index.php/wp-json/wp/v2/tags"}], "about": [{"href": "https://estreetshuffle.com/index.php/wp-json/wp/v2/taxonomies/post_tag"}], "wp:post_type": [{"href": "https://estreetshuffle.com/index.php/wp-json/wp/v2/posts?tags=357"}, {"href": "https://estreetshuffle.com/index.php/wp-json/wp/v2/pages?tags=357"}, {"href": "https://estreetshuffle.com/index.php/wp-json/wp/v2/jetpack-portfolio?tags=357"}], "curies": [{"name": "wp", "href": "https://api.w.org/{rel}", "templated": true}]}}, {"id": 2020, "count": 3, "description": "", "link": "https://estreetshuffle.com/index.php/tag/men-without-women/", "name": "Men Without Women", "slug": "men-without-women", "taxonomy": "post_tag", "meta": [], "_links": {"self": [{"href": "https://estreetshuffle.com/index.php/wp-json/wp/v2/tags/2020", "targetHints": {"allow": ["GET"]}}], "collection": [{"href": "https://estreetshuffle.com/index.php/wp-json/wp/v2/tags"}], "about": [{"href": "https://estreetshuffle.com/index.php/wp-json/wp/v2/taxonomies/post_tag"}], "wp:post_type": [{"href": "https://estreetshuffle.com/index.php/wp-json/wp/v2/posts?tags=2020"}, {"href": "https://estreetshuffle.com/index.php/wp-json/wp/v2/pages?tags=2020"}, {"href": "https://estreetshuffle.com/index.php/wp-json/wp/v2/jetpack-portfolio?tags=2020"}], "curies": [{"name": "wp", "href": "https://api.w.org/{rel}", "templated": true}]}}, {"id": 1688, "count": 1, "description": "", "link": "https://estreetshuffle.com/index.php/tag/mendoza/", "name": "Mendoza", "slug": "mendoza", "taxonomy": "post_tag", "meta": [], "_links": {"self": [{"href": "https://estreetshuffle.com/index.php/wp-json/wp/v2/tags/1688", "targetHints": {"allow": ["GET"]}}], "collection": [{"href": "https://estreetshuffle.com/index.php/wp-json/wp/v2/tags"}], "about": [{"href": "https://estreetshuffle.com/index.php/wp-json/wp/v2/taxonomies/post_tag"}], "wp:post_type": [{"href": "https://estreetshuffle.com/index.php/wp-json/wp/v2/posts?tags=1688"}, {"href": "https://estreetshuffle.com/index.php/wp-json/wp/v2/pages?tags=1688"}, {"href": "https://estreetshuffle.com/index.php/wp-json/wp/v2/jetpack-portfolio?tags=1688"}], "curies": [{"name": "wp", "href": "https://api.w.org/{rel}", "templated": true}]}}, {"id": 3288, "count": 1, "description": "", "link": "https://estreetshuffle.com/index.php/tag/mercy-flight/", "name": "Mercy Flight", "slug": "mercy-flight", "taxonomy": "post_tag", "meta": [], "_links": {"self": [{"href": "https://estreetshuffle.com/index.php/wp-json/wp/v2/tags/3288", "targetHints": {"allow": ["GET"]}}], "collection": [{"href": "https://estreetshuffle.com/index.php/wp-json/wp/v2/tags"}], "about": [{"href": "https://estreetshuffle.com/index.php/wp-json/wp/v2/taxonomies/post_tag"}], "wp:post_type": [{"href": "https://estreetshuffle.com/index.php/wp-json/wp/v2/posts?tags=3288"}, {"href": "https://estreetshuffle.com/index.php/wp-json/wp/v2/pages?tags=3288"}, {"href": "https://estreetshuffle.com/index.php/wp-json/wp/v2/jetpack-portfolio?tags=3288"}], "curies": [{"name": "wp", "href": "https://api.w.org/{rel}", "templated": true}]}}, {"id": 1021, "count": 2, "description": "", "link": "https://estreetshuffle.com/index.php/tag/merlefest/", "name": "MerleFest", "slug": "merlefest", "taxonomy": "post_tag", "meta": [], "_links": {"self": [{"href": "https://estreetshuffle.com/index.php/wp-json/wp/v2/tags/1021", "targetHints": {"allow": ["GET"]}}], "collection": [{"href": "https://estreetshuffle.com/index.php/wp-json/wp/v2/tags"}], "about": [{"href": "https://estreetshuffle.com/index.php/wp-json/wp/v2/taxonomies/post_tag"}], "wp:post_type": [{"href": "https://estreetshuffle.com/index.php/wp-json/wp/v2/posts?tags=1021"}, {"href": "https://estreetshuffle.com/index.php/wp-json/wp/v2/pages?tags=1021"}, {"href": "https://estreetshuffle.com/index.php/wp-json/wp/v2/jetpack-portfolio?tags=1021"}], "curies": [{"name": "wp", "href": "https://api.w.org/{rel}", "templated": true}]}}, {"id": 1981, "count": 9, "description": "", "link": "https://estreetshuffle.com/index.php/tag/merry-christmas-baby/", "name": "Merry Christmas Baby", "slug": "merry-christmas-baby", "taxonomy": "post_tag", "meta": [], "_links": {"self": [{"href": "https://estreetshuffle.com/index.php/wp-json/wp/v2/tags/1981", "targetHints": {"allow": ["GET"]}}], "collection": [{"href": "https://estreetshuffle.com/index.php/wp-json/wp/v2/tags"}], "about": [{"href": "https://estreetshuffle.com/index.php/wp-json/wp/v2/taxonomies/post_tag"}], "wp:post_type": [{"href": "https://estreetshuffle.com/index.php/wp-json/wp/v2/posts?tags=1981"}, {"href": "https://estreetshuffle.com/index.php/wp-json/wp/v2/pages?tags=1981"}, {"href": "https://estreetshuffle.com/index.php/wp-json/wp/v2/jetpack-portfolio?tags=1981"}], "curies": [{"name": "wp", "href": "https://api.w.org/{rel}", "templated": true}]}}, {"id": 191, "count": 1, "description": "", "link": "https://estreetshuffle.com/index.php/tag/meryl-streep/", "name": "Meryl Streep", "slug": "meryl-streep", "taxonomy": "post_tag", "meta": [], "_links": {"self": [{"href": "https://estreetshuffle.com/index.php/wp-json/wp/v2/tags/191", "targetHints": {"allow": ["GET"]}}], "collection": [{"href": "https://estreetshuffle.com/index.php/wp-json/wp/v2/tags"}], "about": [{"href": "https://estreetshuffle.com/index.php/wp-json/wp/v2/taxonomies/post_tag"}], "wp:post_type": [{"href": "https://estreetshuffle.com/index.php/wp-json/wp/v2/posts?tags=191"}, {"href": "https://estreetshuffle.com/index.php/wp-json/wp/v2/pages?tags=191"}, {"href": "https://estreetshuffle.com/index.php/wp-json/wp/v2/jetpack-portfolio?tags=191"}], "curies": [{"name": "wp", "href": "https://api.w.org/{rel}", "templated": true}]}}, {"id": 1466, "count": 1, "description": "", "link": "https://estreetshuffle.com/index.php/tag/message-in-a-bottle/", "name": "Message in a Bottle", "slug": "message-in-a-bottle", "taxonomy": "post_tag", "meta": [], "_links": {"self": [{"href": "https://estreetshuffle.com/index.php/wp-json/wp/v2/tags/1466", "targetHints": {"allow": ["GET"]}}], "collection": [{"href": "https://estreetshuffle.com/index.php/wp-json/wp/v2/tags"}], "about": [{"href": "https://estreetshuffle.com/index.php/wp-json/wp/v2/taxonomies/post_tag"}], "wp:post_type": [{"href": "https://estreetshuffle.com/index.php/wp-json/wp/v2/posts?tags=1466"}, {"href": "https://estreetshuffle.com/index.php/wp-json/wp/v2/pages?tags=1466"}, {"href": "https://estreetshuffle.com/index.php/wp-json/wp/v2/jetpack-portfolio?tags=1466"}], "curies": [{"name": "wp", "href": "https://api.w.org/{rel}", "templated": true}]}}, {"id": 1463, "count": 3, "description": "", "link": "https://estreetshuffle.com/index.php/tag/metlife-stadium/", "name": "Metlife Stadium", "slug": "metlife-stadium", "taxonomy": "post_tag", "meta": [], "_links": {"self": [{"href": "https://estreetshuffle.com/index.php/wp-json/wp/v2/tags/1463", "targetHints": {"allow": ["GET"]}}], "collection": [{"href": "https://estreetshuffle.com/index.php/wp-json/wp/v2/tags"}], "about": [{"href": "https://estreetshuffle.com/index.php/wp-json/wp/v2/taxonomies/post_tag"}], "wp:post_type": [{"href": "https://estreetshuffle.com/index.php/wp-json/wp/v2/posts?tags=1463"}, {"href": "https://estreetshuffle.com/index.php/wp-json/wp/v2/pages?tags=1463"}, {"href": "https://estreetshuffle.com/index.php/wp-json/wp/v2/jetpack-portfolio?tags=1463"}], "curies": [{"name": "wp", "href": "https://api.w.org/{rel}", "templated": true}]}}, {"id": 1977, "count": 1, "description": "", "link": "https://estreetshuffle.com/index.php/tag/mexico/", "name": "Mexico", "slug": "mexico", "taxonomy": "post_tag", "meta": [], "_links": {"self": [{"href": "https://estreetshuffle.com/index.php/wp-json/wp/v2/tags/1977", "targetHints": {"allow": ["GET"]}}], "collection": [{"href": "https://estreetshuffle.com/index.php/wp-json/wp/v2/tags"}], "about": [{"href": "https://estreetshuffle.com/index.php/wp-json/wp/v2/taxonomies/post_tag"}], "wp:post_type": [{"href": "https://estreetshuffle.com/index.php/wp-json/wp/v2/posts?tags=1977"}, {"href": "https://estreetshuffle.com/index.php/wp-json/wp/v2/pages?tags=1977"}, {"href": "https://estreetshuffle.com/index.php/wp-json/wp/v2/jetpack-portfolio?tags=1977"}], "curies": [{"name": "wp", "href": "https://api.w.org/{rel}", "templated": true}]}}, {"id": 1978, "count": 1, "description": "", "link": "https://estreetshuffle.com/index.php/tag/mexico-city/", "name": "Mexico City", "slug": "mexico-city", "taxonomy": "post_tag", "meta": [], "_links": {"self": [{"href": "https://estreetshuffle.com/index.php/wp-json/wp/v2/tags/1978", "targetHints": {"allow": ["GET"]}}], "collection": [{"href": "https://estreetshuffle.com/index.php/wp-json/wp/v2/tags"}], "about": [{"href": "https://estreetshuffle.com/index.php/wp-json/wp/v2/taxonomies/post_tag"}], "wp:post_type": [{"href": "https://estreetshuffle.com/index.php/wp-json/wp/v2/posts?tags=1978"}, {"href": "https://estreetshuffle.com/index.php/wp-json/wp/v2/pages?tags=1978"}, {"href": "https://estreetshuffle.com/index.php/wp-json/wp/v2/jetpack-portfolio?tags=1978"}], "curies": [{"name": "wp", "href": "https://api.w.org/{rel}", "templated": true}]}}, {"id": 459, "count": 9, "description": "", "link": "https://estreetshuffle.com/index.php/tag/miami/", "name": "Miami", "slug": "miami", "taxonomy": "post_tag", "meta": [], "_links": {"self": [{"href": "https://estreetshuffle.com/index.php/wp-json/wp/v2/tags/459", "targetHints": {"allow": ["GET"]}}], "collection": [{"href": "https://estreetshuffle.com/index.php/wp-json/wp/v2/tags"}], "about": [{"href": "https://estreetshuffle.com/index.php/wp-json/wp/v2/taxonomies/post_tag"}], "wp:post_type": [{"href": "https://estreetshuffle.com/index.php/wp-json/wp/v2/posts?tags=459"}, {"href": "https://estreetshuffle.com/index.php/wp-json/wp/v2/pages?tags=459"}, {"href": "https://estreetshuffle.com/index.php/wp-json/wp/v2/jetpack-portfolio?tags=459"}], "curies": [{"name": "wp", "href": "https://api.w.org/{rel}", "templated": true}]}}, {"id": 1209, "count": 12, "description": "", "link": "https://estreetshuffle.com/index.php/tag/miami-horns/", "name": "Miami Horns", "slug": "miami-horns", "taxonomy": "post_tag", "meta": [], "_links": {"self": [{"href": "https://estreetshuffle.com/index.php/wp-json/wp/v2/tags/1209", "targetHints": {"allow": ["GET"]}}], "collection": [{"href": "https://estreetshuffle.com/index.php/wp-json/wp/v2/tags"}], "about": [{"href": "https://estreetshuffle.com/index.php/wp-json/wp/v2/taxonomies/post_tag"}], "wp:post_type": [{"href": "https://estreetshuffle.com/index.php/wp-json/wp/v2/posts?tags=1209"}, {"href": "https://estreetshuffle.com/index.php/wp-json/wp/v2/pages?tags=1209"}, {"href": "https://estreetshuffle.com/index.php/wp-json/wp/v2/jetpack-portfolio?tags=1209"}], "curies": [{"name": "wp", "href": "https://api.w.org/{rel}", "templated": true}]}}, {"id": 2274, "count": 1, "description": "", "link": "https://estreetshuffle.com/index.php/tag/michael-bloomberg/", "name": "Michael Bloomberg", "slug": "michael-bloomberg", "taxonomy": "post_tag", "meta": [], "_links": {"self": [{"href": "https://estreetshuffle.com/index.php/wp-json/wp/v2/tags/2274", "targetHints": {"allow": ["GET"]}}], "collection": [{"href": "https://estreetshuffle.com/index.php/wp-json/wp/v2/tags"}], "about": [{"href": "https://estreetshuffle.com/index.php/wp-json/wp/v2/taxonomies/post_tag"}], "wp:post_type": [{"href": "https://estreetshuffle.com/index.php/wp-json/wp/v2/posts?tags=2274"}, {"href": "https://estreetshuffle.com/index.php/wp-json/wp/v2/pages?tags=2274"}, {"href": "https://estreetshuffle.com/index.php/wp-json/wp/v2/jetpack-portfolio?tags=2274"}], "curies": [{"name": "wp", "href": "https://api.w.org/{rel}", "templated": true}]}}, {"id": 3441, "count": 1, "description": "", "link": "https://estreetshuffle.com/index.php/tag/michael-gudinski/", "name": "Michael Gudinski", "slug": "michael-gudinski", "taxonomy": "post_tag", "meta": [], "_links": {"self": [{"href": "https://estreetshuffle.com/index.php/wp-json/wp/v2/tags/3441", "targetHints": {"allow": ["GET"]}}], "collection": [{"href": "https://estreetshuffle.com/index.php/wp-json/wp/v2/tags"}], "about": [{"href": "https://estreetshuffle.com/index.php/wp-json/wp/v2/taxonomies/post_tag"}], "wp:post_type": [{"href": "https://estreetshuffle.com/index.php/wp-json/wp/v2/posts?tags=3441"}, {"href": "https://estreetshuffle.com/index.php/wp-json/wp/v2/pages?tags=3441"}, {"href": "https://estreetshuffle.com/index.php/wp-json/wp/v2/jetpack-portfolio?tags=3441"}], "curies": [{"name": "wp", "href": "https://api.w.org/{rel}", "templated": true}]}}, {"id": 1818, "count": 2, "description": "", "link": "https://estreetshuffle.com/index.php/tag/michael-j-fox/", "name": "Michael J. Fox", "slug": "michael-j-fox", "taxonomy": "post_tag", "meta": [], "_links": {"self": [{"href": "https://estreetshuffle.com/index.php/wp-json/wp/v2/tags/1818", "targetHints": {"allow": ["GET"]}}], "collection": [{"href": "https://estreetshuffle.com/index.php/wp-json/wp/v2/tags"}], "about": [{"href": "https://estreetshuffle.com/index.php/wp-json/wp/v2/taxonomies/post_tag"}], "wp:post_type": [{"href": "https://estreetshuffle.com/index.php/wp-json/wp/v2/posts?tags=1818"}, {"href": "https://estreetshuffle.com/index.php/wp-json/wp/v2/pages?tags=1818"}, {"href": "https://estreetshuffle.com/index.php/wp-json/wp/v2/jetpack-portfolio?tags=1818"}], "curies": [{"name": "wp", "href": "https://api.w.org/{rel}", "templated": true}]}}, {"id": 3242, "count": 1, "description": "", "link": "https://estreetshuffle.com/index.php/tag/michael-jackson/", "name": "Michael Jackson", "slug": "michael-jackson", "taxonomy": "post_tag", "meta": [], "_links": {"self": [{"href": "https://estreetshuffle.com/index.php/wp-json/wp/v2/tags/3242", "targetHints": {"allow": ["GET"]}}], "collection": [{"href": "https://estreetshuffle.com/index.php/wp-json/wp/v2/tags"}], "about": [{"href": "https://estreetshuffle.com/index.php/wp-json/wp/v2/taxonomies/post_tag"}], "wp:post_type": [{"href": "https://estreetshuffle.com/index.php/wp-json/wp/v2/posts?tags=3242"}, {"href": "https://estreetshuffle.com/index.php/wp-json/wp/v2/pages?tags=3242"}, {"href": "https://estreetshuffle.com/index.php/wp-json/wp/v2/jetpack-portfolio?tags=3242"}], "curies": [{"name": "wp", "href": "https://api.w.org/{rel}", "templated": true}]}}, {"id": 2721, "count": 1, "description": "", "link": "https://estreetshuffle.com/index.php/tag/michael-petrella/", "name": "Michael Petrella", "slug": "michael-petrella", "taxonomy": "post_tag", "meta": [], "_links": {"self": [{"href": "https://estreetshuffle.com/index.php/wp-json/wp/v2/tags/2721", "targetHints": {"allow": ["GET"]}}], "collection": [{"href": "https://estreetshuffle.com/index.php/wp-json/wp/v2/tags"}], "about": [{"href": "https://estreetshuffle.com/index.php/wp-json/wp/v2/taxonomies/post_tag"}], "wp:post_type": [{"href": "https://estreetshuffle.com/index.php/wp-json/wp/v2/posts?tags=2721"}, {"href": "https://estreetshuffle.com/index.php/wp-json/wp/v2/pages?tags=2721"}, {"href": "https://estreetshuffle.com/index.php/wp-json/wp/v2/jetpack-portfolio?tags=2721"}], "curies": [{"name": "wp", "href": "https://api.w.org/{rel}", "templated": true}]}}, {"id": 1139, "count": 1, "description": "", "link": "https://estreetshuffle.com/index.php/tag/michael-stipe/", "name": "Michael Stipe", "slug": "michael-stipe", "taxonomy": "post_tag", "meta": [], "_links": {"self": [{"href": "https://estreetshuffle.com/index.php/wp-json/wp/v2/tags/1139", "targetHints": {"allow": ["GET"]}}], "collection": [{"href": "https://estreetshuffle.com/index.php/wp-json/wp/v2/tags"}], "about": [{"href": "https://estreetshuffle.com/index.php/wp-json/wp/v2/taxonomies/post_tag"}], "wp:post_type": [{"href": "https://estreetshuffle.com/index.php/wp-json/wp/v2/posts?tags=1139"}, {"href": "https://estreetshuffle.com/index.php/wp-json/wp/v2/pages?tags=1139"}, {"href": "https://estreetshuffle.com/index.php/wp-json/wp/v2/jetpack-portfolio?tags=1139"}], "curies": [{"name": "wp", "href": "https://api.w.org/{rel}", "templated": true}]}}, {"id": 2200, "count": 2, "description": "", "link": "https://estreetshuffle.com/index.php/tag/michael-strollo/", "name": "Michael Strollo", "slug": "michael-strollo", "taxonomy": "post_tag", "meta": [], "_links": {"self": [{"href": "https://estreetshuffle.com/index.php/wp-json/wp/v2/tags/2200", "targetHints": {"allow": ["GET"]}}], "collection": [{"href": "https://estreetshuffle.com/index.php/wp-json/wp/v2/tags"}], "about": [{"href": "https://estreetshuffle.com/index.php/wp-json/wp/v2/taxonomies/post_tag"}], "wp:post_type": [{"href": "https://estreetshuffle.com/index.php/wp-json/wp/v2/posts?tags=2200"}, {"href": "https://estreetshuffle.com/index.php/wp-json/wp/v2/pages?tags=2200"}, {"href": "https://estreetshuffle.com/index.php/wp-json/wp/v2/jetpack-portfolio?tags=2200"}], "curies": [{"name": "wp", "href": "https://api.w.org/{rel}", "templated": true}]}}, {"id": 1176, "count": 4, "description": "", "link": "https://estreetshuffle.com/index.php/tag/michelle-moore/", "name": "Michelle Moore", "slug": "michelle-moore", "taxonomy": "post_tag", "meta": [], "_links": {"self": [{"href": "https://estreetshuffle.com/index.php/wp-json/wp/v2/tags/1176", "targetHints": {"allow": ["GET"]}}], "collection": [{"href": "https://estreetshuffle.com/index.php/wp-json/wp/v2/tags"}], "about": [{"href": "https://estreetshuffle.com/index.php/wp-json/wp/v2/taxonomies/post_tag"}], "wp:post_type": [{"href": "https://estreetshuffle.com/index.php/wp-json/wp/v2/posts?tags=1176"}, {"href": "https://estreetshuffle.com/index.php/wp-json/wp/v2/pages?tags=1176"}, {"href": "https://estreetshuffle.com/index.php/wp-json/wp/v2/jetpack-portfolio?tags=1176"}], "curies": [{"name": "wp", "href": "https://api.w.org/{rel}", "templated": true}]}}, {"id": 2447, "count": 2, "description": "", "link": "https://estreetshuffle.com/index.php/tag/michelle-obama/", "name": "Michelle Obama", "slug": "michelle-obama", "taxonomy": "post_tag", "meta": [], "_links": {"self": [{"href": "https://estreetshuffle.com/index.php/wp-json/wp/v2/tags/2447", "targetHints": {"allow": ["GET"]}}], "collection": [{"href": "https://estreetshuffle.com/index.php/wp-json/wp/v2/tags"}], "about": [{"href": "https://estreetshuffle.com/index.php/wp-json/wp/v2/taxonomies/post_tag"}], "wp:post_type": [{"href": "https://estreetshuffle.com/index.php/wp-json/wp/v2/posts?tags=2447"}, {"href": "https://estreetshuffle.com/index.php/wp-json/wp/v2/pages?tags=2447"}, {"href": "https://estreetshuffle.com/index.php/wp-json/wp/v2/jetpack-portfolio?tags=2447"}], "curies": [{"name": "wp", "href": "https://api.w.org/{rel}", "templated": true}]}}, {"id": 612, "count": 1, "description": "", "link": "https://estreetshuffle.com/index.php/tag/michigan/", "name": "Michigan", "slug": "michigan", "taxonomy": "post_tag", "meta": [], "_links": {"self": [{"href": "https://estreetshuffle.com/index.php/wp-json/wp/v2/tags/612", "targetHints": {"allow": ["GET"]}}], "collection": [{"href": "https://estreetshuffle.com/index.php/wp-json/wp/v2/tags"}], "about": [{"href": "https://estreetshuffle.com/index.php/wp-json/wp/v2/taxonomies/post_tag"}], "wp:post_type": [{"href": "https://estreetshuffle.com/index.php/wp-json/wp/v2/posts?tags=612"}, {"href": "https://estreetshuffle.com/index.php/wp-json/wp/v2/pages?tags=612"}, {"href": "https://estreetshuffle.com/index.php/wp-json/wp/v2/jetpack-portfolio?tags=612"}], "curies": [{"name": "wp", "href": "https://api.w.org/{rel}", "templated": true}]}}, {"id": 870, "count": 7, "description": "", "link": "https://estreetshuffle.com/index.php/tag/mick-jagger/", "name": "Mick Jagger", "slug": "mick-jagger", "taxonomy": "post_tag", "meta": [], "_links": {"self": [{"href": "https://estreetshuffle.com/index.php/wp-json/wp/v2/tags/870", "targetHints": {"allow": ["GET"]}}], "collection": [{"href": "https://estreetshuffle.com/index.php/wp-json/wp/v2/tags"}], "about": [{"href": "https://estreetshuffle.com/index.php/wp-json/wp/v2/taxonomies/post_tag"}], "wp:post_type": [{"href": "https://estreetshuffle.com/index.php/wp-json/wp/v2/posts?tags=870"}, {"href": "https://estreetshuffle.com/index.php/wp-json/wp/v2/pages?tags=870"}, {"href": "https://estreetshuffle.com/index.php/wp-json/wp/v2/jetpack-portfolio?tags=870"}], "curies": [{"name": "wp", "href": "https://api.w.org/{rel}", "templated": true}]}}, {"id": 3462, "count": 1, "description": "", "link": "https://estreetshuffle.com/index.php/tag/mick-stender/", "name": "Mick Stender", "slug": "mick-stender", "taxonomy": "post_tag", "meta": [], "_links": {"self": [{"href": "https://estreetshuffle.com/index.php/wp-json/wp/v2/tags/3462", "targetHints": {"allow": ["GET"]}}], "collection": [{"href": "https://estreetshuffle.com/index.php/wp-json/wp/v2/tags"}], "about": [{"href": "https://estreetshuffle.com/index.php/wp-json/wp/v2/taxonomies/post_tag"}], "wp:post_type": [{"href": "https://estreetshuffle.com/index.php/wp-json/wp/v2/posts?tags=3462"}, {"href": "https://estreetshuffle.com/index.php/wp-json/wp/v2/pages?tags=3462"}, {"href": "https://estreetshuffle.com/index.php/wp-json/wp/v2/jetpack-portfolio?tags=3462"}], "curies": [{"name": "wp", "href": "https://api.w.org/{rel}", "templated": true}]}}, {"id": 2225, "count": 1, "description": "", "link": "https://estreetshuffle.com/index.php/tag/mickey-rourke/", "name": "Mickey Rourke", "slug": "mickey-rourke", "taxonomy": "post_tag", "meta": [], "_links": {"self": [{"href": "https://estreetshuffle.com/index.php/wp-json/wp/v2/tags/2225", "targetHints": {"allow": ["GET"]}}], "collection": [{"href": "https://estreetshuffle.com/index.php/wp-json/wp/v2/tags"}], "about": [{"href": "https://estreetshuffle.com/index.php/wp-json/wp/v2/taxonomies/post_tag"}], "wp:post_type": [{"href": "https://estreetshuffle.com/index.php/wp-json/wp/v2/posts?tags=2225"}, {"href": "https://estreetshuffle.com/index.php/wp-json/wp/v2/pages?tags=2225"}, {"href": "https://estreetshuffle.com/index.php/wp-json/wp/v2/jetpack-portfolio?tags=2225"}], "curies": [{"name": "wp", "href": "https://api.w.org/{rel}", "templated": true}]}}, {"id": 2223, "count": 0, "description": "", "link": "https://estreetshuffle.com/index.php/tag/micky-rourke/", "name": "Micky Rourke", "slug": "micky-rourke", "taxonomy": "post_tag", "meta": [], "_links": {"self": [{"href": "https://estreetshuffle.com/index.php/wp-json/wp/v2/tags/2223", "targetHints": {"allow": ["GET"]}}], "collection": [{"href": "https://estreetshuffle.com/index.php/wp-json/wp/v2/tags"}], "about": [{"href": "https://estreetshuffle.com/index.php/wp-json/wp/v2/taxonomies/post_tag"}], "wp:post_type": [{"href": "https://estreetshuffle.com/index.php/wp-json/wp/v2/posts?tags=2223"}, {"href": "https://estreetshuffle.com/index.php/wp-json/wp/v2/pages?tags=2223"}, {"href": "https://estreetshuffle.com/index.php/wp-json/wp/v2/jetpack-portfolio?tags=2223"}], "curies": [{"name": "wp", "href": "https://api.w.org/{rel}", "templated": true}]}}, {"id": 2971, "count": 1, "description": "", "link": "https://estreetshuffle.com/index.php/tag/micol-picchioni/", "name": "Micol Picchioni", "slug": "micol-picchioni", "taxonomy": "post_tag", "meta": [], "_links": {"self": [{"href": "https://estreetshuffle.com/index.php/wp-json/wp/v2/tags/2971", "targetHints": {"allow": ["GET"]}}], "collection": [{"href": "https://estreetshuffle.com/index.php/wp-json/wp/v2/tags"}], "about": [{"href": "https://estreetshuffle.com/index.php/wp-json/wp/v2/taxonomies/post_tag"}], "wp:post_type": [{"href": "https://estreetshuffle.com/index.php/wp-json/wp/v2/posts?tags=2971"}, {"href": "https://estreetshuffle.com/index.php/wp-json/wp/v2/pages?tags=2971"}, {"href": "https://estreetshuffle.com/index.php/wp-json/wp/v2/jetpack-portfolio?tags=2971"}], "curies": [{"name": "wp", "href": "https://api.w.org/{rel}", "templated": true}]}}, {"id": 1291, "count": 1, "description": "", "link": "https://estreetshuffle.com/index.php/tag/midnight-thunder/", "name": "Midnight Thunder", "slug": "midnight-thunder", "taxonomy": "post_tag", "meta": [], "_links": {"self": [{"href": "https://estreetshuffle.com/index.php/wp-json/wp/v2/tags/1291", "targetHints": {"allow": ["GET"]}}], "collection": [{"href": "https://estreetshuffle.com/index.php/wp-json/wp/v2/tags"}], "about": [{"href": "https://estreetshuffle.com/index.php/wp-json/wp/v2/taxonomies/post_tag"}], "wp:post_type": [{"href": "https://estreetshuffle.com/index.php/wp-json/wp/v2/posts?tags=1291"}, {"href": "https://estreetshuffle.com/index.php/wp-json/wp/v2/pages?tags=1291"}, {"href": "https://estreetshuffle.com/index.php/wp-json/wp/v2/jetpack-portfolio?tags=1291"}], "curies": [{"name": "wp", "href": "https://api.w.org/{rel}", "templated": true}]}}, {"id": 453, "count": 2, "description": "", "link": "https://estreetshuffle.com/index.php/tag/midnight-train/", "name": "Midnight Train", "slug": "midnight-train", "taxonomy": "post_tag", "meta": [], "_links": {"self": [{"href": "https://estreetshuffle.com/index.php/wp-json/wp/v2/tags/453", "targetHints": {"allow": ["GET"]}}], "collection": [{"href": "https://estreetshuffle.com/index.php/wp-json/wp/v2/tags"}], "about": [{"href": "https://estreetshuffle.com/index.php/wp-json/wp/v2/taxonomies/post_tag"}], "wp:post_type": [{"href": "https://estreetshuffle.com/index.php/wp-json/wp/v2/posts?tags=453"}, {"href": "https://estreetshuffle.com/index.php/wp-json/wp/v2/pages?tags=453"}, {"href": "https://estreetshuffle.com/index.php/wp-json/wp/v2/jetpack-portfolio?tags=453"}], "curies": [{"name": "wp", "href": "https://api.w.org/{rel}", "templated": true}]}}, {"id": 290, "count": 13, "description": "", "link": "https://estreetshuffle.com/index.php/tag/mike-appel/", "name": "Mike Appel", "slug": "mike-appel", "taxonomy": "post_tag", "meta": [], "_links": {"self": [{"href": "https://estreetshuffle.com/index.php/wp-json/wp/v2/tags/290", "targetHints": {"allow": ["GET"]}}], "collection": [{"href": "https://estreetshuffle.com/index.php/wp-json/wp/v2/tags"}], "about": [{"href": "https://estreetshuffle.com/index.php/wp-json/wp/v2/taxonomies/post_tag"}], "wp:post_type": [{"href": "https://estreetshuffle.com/index.php/wp-json/wp/v2/posts?tags=290"}, {"href": "https://estreetshuffle.com/index.php/wp-json/wp/v2/pages?tags=290"}, {"href": "https://estreetshuffle.com/index.php/wp-json/wp/v2/jetpack-portfolio?tags=290"}], "curies": [{"name": "wp", "href": "https://api.w.org/{rel}", "templated": true}]}}, {"id": 3406, "count": 1, "description": "", "link": "https://estreetshuffle.com/index.php/tag/mike-love/", "name": "Mike Love", "slug": "mike-love", "taxonomy": "post_tag", "meta": [], "_links": {"self": [{"href": "https://estreetshuffle.com/index.php/wp-json/wp/v2/tags/3406", "targetHints": {"allow": ["GET"]}}], "collection": [{"href": "https://estreetshuffle.com/index.php/wp-json/wp/v2/tags"}], "about": [{"href": "https://estreetshuffle.com/index.php/wp-json/wp/v2/taxonomies/post_tag"}], "wp:post_type": [{"href": "https://estreetshuffle.com/index.php/wp-json/wp/v2/posts?tags=3406"}, {"href": "https://estreetshuffle.com/index.php/wp-json/wp/v2/pages?tags=3406"}, {"href": "https://estreetshuffle.com/index.php/wp-json/wp/v2/jetpack-portfolio?tags=3406"}], "curies": [{"name": "wp", "href": "https://api.w.org/{rel}", "templated": true}]}}, {"id": 708, "count": 6, "description": "", "link": "https://estreetshuffle.com/index.php/tag/mike-ness/", "name": "Mike Ness", "slug": "mike-ness", "taxonomy": "post_tag", "meta": [], "_links": {"self": [{"href": "https://estreetshuffle.com/index.php/wp-json/wp/v2/tags/708", "targetHints": {"allow": ["GET"]}}], "collection": [{"href": "https://estreetshuffle.com/index.php/wp-json/wp/v2/tags"}], "about": [{"href": "https://estreetshuffle.com/index.php/wp-json/wp/v2/taxonomies/post_tag"}], "wp:post_type": [{"href": "https://estreetshuffle.com/index.php/wp-json/wp/v2/posts?tags=708"}, {"href": "https://estreetshuffle.com/index.php/wp-json/wp/v2/pages?tags=708"}, {"href": "https://estreetshuffle.com/index.php/wp-json/wp/v2/jetpack-portfolio?tags=708"}], "curies": [{"name": "wp", "href": "https://api.w.org/{rel}", "templated": true}]}}, {"id": 1767, "count": 1, "description": "", "link": "https://estreetshuffle.com/index.php/tag/mike-porco/", "name": "Mike Porco", "slug": "mike-porco", "taxonomy": "post_tag", "meta": [], "_links": {"self": [{"href": "https://estreetshuffle.com/index.php/wp-json/wp/v2/tags/1767", "targetHints": {"allow": ["GET"]}}], "collection": [{"href": "https://estreetshuffle.com/index.php/wp-json/wp/v2/tags"}], "about": [{"href": "https://estreetshuffle.com/index.php/wp-json/wp/v2/taxonomies/post_tag"}], "wp:post_type": [{"href": "https://estreetshuffle.com/index.php/wp-json/wp/v2/posts?tags=1767"}, {"href": "https://estreetshuffle.com/index.php/wp-json/wp/v2/pages?tags=1767"}, {"href": "https://estreetshuffle.com/index.php/wp-json/wp/v2/jetpack-portfolio?tags=1767"}], "curies": [{"name": "wp", "href": "https://api.w.org/{rel}", "templated": true}]}}, {"id": 661, "count": 14, "description": "", "link": "https://estreetshuffle.com/index.php/tag/milan/", "name": "Milan", "slug": "milan", "taxonomy": "post_tag", "meta": [], "_links": {"self": [{"href": "https://estreetshuffle.com/index.php/wp-json/wp/v2/tags/661", "targetHints": {"allow": ["GET"]}}], "collection": [{"href": "https://estreetshuffle.com/index.php/wp-json/wp/v2/tags"}], "about": [{"href": "https://estreetshuffle.com/index.php/wp-json/wp/v2/taxonomies/post_tag"}], "wp:post_type": [{"href": "https://estreetshuffle.com/index.php/wp-json/wp/v2/posts?tags=661"}, {"href": "https://estreetshuffle.com/index.php/wp-json/wp/v2/pages?tags=661"}, {"href": "https://estreetshuffle.com/index.php/wp-json/wp/v2/jetpack-portfolio?tags=661"}], "curies": [{"name": "wp", "href": "https://api.w.org/{rel}", "templated": true}]}}, {"id": 2621, "count": 1, "description": "", "link": "https://estreetshuffle.com/index.php/tag/millwork/", "name": "Millwork", "slug": "millwork", "taxonomy": "post_tag", "meta": [], "_links": {"self": [{"href": "https://estreetshuffle.com/index.php/wp-json/wp/v2/tags/2621", "targetHints": {"allow": ["GET"]}}], "collection": [{"href": "https://estreetshuffle.com/index.php/wp-json/wp/v2/tags"}], "about": [{"href": "https://estreetshuffle.com/index.php/wp-json/wp/v2/taxonomies/post_tag"}], "wp:post_type": [{"href": "https://estreetshuffle.com/index.php/wp-json/wp/v2/posts?tags=2621"}, {"href": "https://estreetshuffle.com/index.php/wp-json/wp/v2/pages?tags=2621"}, {"href": "https://estreetshuffle.com/index.php/wp-json/wp/v2/jetpack-portfolio?tags=2621"}], "curies": [{"name": "wp", "href": "https://api.w.org/{rel}", "templated": true}]}}, {"id": 224, "count": 2, "description": "", "link": "https://estreetshuffle.com/index.php/tag/millworker/", "name": "Millworker", "slug": "millworker", "taxonomy": "post_tag", "meta": [], "_links": {"self": [{"href": "https://estreetshuffle.com/index.php/wp-json/wp/v2/tags/224", "targetHints": {"allow": ["GET"]}}], "collection": [{"href": "https://estreetshuffle.com/index.php/wp-json/wp/v2/tags"}], "about": [{"href": "https://estreetshuffle.com/index.php/wp-json/wp/v2/taxonomies/post_tag"}], "wp:post_type": [{"href": "https://estreetshuffle.com/index.php/wp-json/wp/v2/posts?tags=224"}, {"href": "https://estreetshuffle.com/index.php/wp-json/wp/v2/pages?tags=224"}, {"href": "https://estreetshuffle.com/index.php/wp-json/wp/v2/jetpack-portfolio?tags=224"}], "curies": [{"name": "wp", "href": "https://api.w.org/{rel}", "templated": true}]}}, {"id": 996, "count": 1, "description": "", "link": "https://estreetshuffle.com/index.php/tag/milton-keynes/", "name": "Milton Keynes", "slug": "milton-keynes", "taxonomy": "post_tag", "meta": [], "_links": {"self": [{"href": "https://estreetshuffle.com/index.php/wp-json/wp/v2/tags/996", "targetHints": {"allow": ["GET"]}}], "collection": [{"href": "https://estreetshuffle.com/index.php/wp-json/wp/v2/tags"}], "about": [{"href": "https://estreetshuffle.com/index.php/wp-json/wp/v2/taxonomies/post_tag"}], "wp:post_type": [{"href": "https://estreetshuffle.com/index.php/wp-json/wp/v2/posts?tags=996"}, {"href": "https://estreetshuffle.com/index.php/wp-json/wp/v2/pages?tags=996"}, {"href": "https://estreetshuffle.com/index.php/wp-json/wp/v2/jetpack-portfolio?tags=996"}], "curies": [{"name": "wp", "href": "https://api.w.org/{rel}", "templated": true}]}}, {"id": 345, "count": 15, "description": "", "link": "https://estreetshuffle.com/index.php/tag/milwaukee/", "name": "Milwaukee", "slug": "milwaukee", "taxonomy": "post_tag", "meta": [], "_links": {"self": [{"href": "https://estreetshuffle.com/index.php/wp-json/wp/v2/tags/345", "targetHints": {"allow": ["GET"]}}], "collection": [{"href": "https://estreetshuffle.com/index.php/wp-json/wp/v2/tags"}], "about": [{"href": "https://estreetshuffle.com/index.php/wp-json/wp/v2/taxonomies/post_tag"}], "wp:post_type": [{"href": "https://estreetshuffle.com/index.php/wp-json/wp/v2/posts?tags=345"}, {"href": "https://estreetshuffle.com/index.php/wp-json/wp/v2/pages?tags=345"}, {"href": "https://estreetshuffle.com/index.php/wp-json/wp/v2/jetpack-portfolio?tags=345"}], "curies": [{"name": "wp", "href": "https://api.w.org/{rel}", "templated": true}]}}, {"id": 1591, "count": 6, "description": "", "link": "https://estreetshuffle.com/index.php/tag/minneapolis/", "name": "Minneapolis", "slug": "minneapolis", "taxonomy": "post_tag", "meta": [], "_links": {"self": [{"href": "https://estreetshuffle.com/index.php/wp-json/wp/v2/tags/1591", "targetHints": {"allow": ["GET"]}}], "collection": [{"href": "https://estreetshuffle.com/index.php/wp-json/wp/v2/tags"}], "about": [{"href": "https://estreetshuffle.com/index.php/wp-json/wp/v2/taxonomies/post_tag"}], "wp:post_type": [{"href": "https://estreetshuffle.com/index.php/wp-json/wp/v2/posts?tags=1591"}, {"href": "https://estreetshuffle.com/index.php/wp-json/wp/v2/pages?tags=1591"}, {"href": "https://estreetshuffle.com/index.php/wp-json/wp/v2/jetpack-portfolio?tags=1591"}], "curies": [{"name": "wp", "href": "https://api.w.org/{rel}", "templated": true}]}}, {"id": 2403, "count": 1, "description": "", "link": "https://estreetshuffle.com/index.php/tag/minnie-driver/", "name": "Minnie Driver", "slug": "minnie-driver", "taxonomy": "post_tag", "meta": [], "_links": {"self": [{"href": "https://estreetshuffle.com/index.php/wp-json/wp/v2/tags/2403", "targetHints": {"allow": ["GET"]}}], "collection": [{"href": "https://estreetshuffle.com/index.php/wp-json/wp/v2/tags"}], "about": [{"href": "https://estreetshuffle.com/index.php/wp-json/wp/v2/taxonomies/post_tag"}], "wp:post_type": [{"href": "https://estreetshuffle.com/index.php/wp-json/wp/v2/posts?tags=2403"}, {"href": "https://estreetshuffle.com/index.php/wp-json/wp/v2/pages?tags=2403"}, {"href": "https://estreetshuffle.com/index.php/wp-json/wp/v2/jetpack-portfolio?tags=2403"}], "curies": [{"name": "wp", "href": "https://api.w.org/{rel}", "templated": true}]}}, {"id": 2004, "count": 2, "description": "", "link": "https://estreetshuffle.com/index.php/tag/misery-loves-company/", "name": "Misery Loves Company", "slug": "misery-loves-company", "taxonomy": "post_tag", "meta": [], "_links": {"self": [{"href": "https://estreetshuffle.com/index.php/wp-json/wp/v2/tags/2004", "targetHints": {"allow": ["GET"]}}], "collection": [{"href": "https://estreetshuffle.com/index.php/wp-json/wp/v2/tags"}], "about": [{"href": "https://estreetshuffle.com/index.php/wp-json/wp/v2/taxonomies/post_tag"}], "wp:post_type": [{"href": "https://estreetshuffle.com/index.php/wp-json/wp/v2/posts?tags=2004"}, {"href": "https://estreetshuffle.com/index.php/wp-json/wp/v2/pages?tags=2004"}, {"href": "https://estreetshuffle.com/index.php/wp-json/wp/v2/jetpack-portfolio?tags=2004"}], "curies": [{"name": "wp", "href": "https://api.w.org/{rel}", "templated": true}]}}, {"id": 1205, "count": 1, "description": "", "link": "https://estreetshuffle.com/index.php/tag/miss-piggy/", "name": "Miss Piggy", "slug": "miss-piggy", "taxonomy": "post_tag", "meta": [], "_links": {"self": [{"href": "https://estreetshuffle.com/index.php/wp-json/wp/v2/tags/1205", "targetHints": {"allow": ["GET"]}}], "collection": [{"href": "https://estreetshuffle.com/index.php/wp-json/wp/v2/tags"}], "about": [{"href": "https://estreetshuffle.com/index.php/wp-json/wp/v2/taxonomies/post_tag"}], "wp:post_type": [{"href": "https://estreetshuffle.com/index.php/wp-json/wp/v2/posts?tags=1205"}, {"href": "https://estreetshuffle.com/index.php/wp-json/wp/v2/pages?tags=1205"}, {"href": "https://estreetshuffle.com/index.php/wp-json/wp/v2/jetpack-portfolio?tags=1205"}], "curies": [{"name": "wp", "href": "https://api.w.org/{rel}", "templated": true}]}}, {"id": 3045, "count": 1, "description": "", "link": "https://estreetshuffle.com/index.php/tag/missing/", "name": "Missing", "slug": "missing", "taxonomy": "post_tag", "meta": [], "_links": {"self": [{"href": "https://estreetshuffle.com/index.php/wp-json/wp/v2/tags/3045", "targetHints": {"allow": ["GET"]}}], "collection": [{"href": "https://estreetshuffle.com/index.php/wp-json/wp/v2/tags"}], "about": [{"href": "https://estreetshuffle.com/index.php/wp-json/wp/v2/taxonomies/post_tag"}], "wp:post_type": [{"href": "https://estreetshuffle.com/index.php/wp-json/wp/v2/posts?tags=3045"}, {"href": "https://estreetshuffle.com/index.php/wp-json/wp/v2/pages?tags=3045"}, {"href": "https://estreetshuffle.com/index.php/wp-json/wp/v2/jetpack-portfolio?tags=3045"}], "curies": [{"name": "wp", "href": "https://api.w.org/{rel}", "templated": true}]}}, {"id": 288, "count": 2, "description": "", "link": "https://estreetshuffle.com/index.php/tag/mississippi/", "name": "Mississippi", "slug": "mississippi", "taxonomy": "post_tag", "meta": [], "_links": {"self": [{"href": "https://estreetshuffle.com/index.php/wp-json/wp/v2/tags/288", "targetHints": {"allow": ["GET"]}}], "collection": [{"href": "https://estreetshuffle.com/index.php/wp-json/wp/v2/tags"}], "about": [{"href": "https://estreetshuffle.com/index.php/wp-json/wp/v2/taxonomies/post_tag"}], "wp:post_type": [{"href": "https://estreetshuffle.com/index.php/wp-json/wp/v2/posts?tags=288"}, {"href": "https://estreetshuffle.com/index.php/wp-json/wp/v2/pages?tags=288"}, {"href": "https://estreetshuffle.com/index.php/wp-json/wp/v2/jetpack-portfolio?tags=288"}], "curies": [{"name": "wp", "href": "https://api.w.org/{rel}", "templated": true}]}}, {"id": 1928, "count": 1, "description": "", "link": "https://estreetshuffle.com/index.php/tag/mississippi-sheiks/", "name": "Mississippi Sheiks", "slug": "mississippi-sheiks", "taxonomy": "post_tag", "meta": [], "_links": {"self": [{"href": "https://estreetshuffle.com/index.php/wp-json/wp/v2/tags/1928", "targetHints": {"allow": ["GET"]}}], "collection": [{"href": "https://estreetshuffle.com/index.php/wp-json/wp/v2/tags"}], "about": [{"href": "https://estreetshuffle.com/index.php/wp-json/wp/v2/taxonomies/post_tag"}], "wp:post_type": [{"href": "https://estreetshuffle.com/index.php/wp-json/wp/v2/posts?tags=1928"}, {"href": "https://estreetshuffle.com/index.php/wp-json/wp/v2/pages?tags=1928"}, {"href": "https://estreetshuffle.com/index.php/wp-json/wp/v2/jetpack-portfolio?tags=1928"}], "curies": [{"name": "wp", "href": "https://api.w.org/{rel}", "templated": true}]}}, {"id": 2068, "count": 1, "description": "", "link": "https://estreetshuffle.com/index.php/tag/mistress-annie/", "name": "Mistress Annie", "slug": "mistress-annie", "taxonomy": "post_tag", "meta": [], "_links": {"self": [{"href": "https://estreetshuffle.com/index.php/wp-json/wp/v2/tags/2068", "targetHints": {"allow": ["GET"]}}], "collection": [{"href": "https://estreetshuffle.com/index.php/wp-json/wp/v2/tags"}], "about": [{"href": "https://estreetshuffle.com/index.php/wp-json/wp/v2/taxonomies/post_tag"}], "wp:post_type": [{"href": "https://estreetshuffle.com/index.php/wp-json/wp/v2/posts?tags=2068"}, {"href": "https://estreetshuffle.com/index.php/wp-json/wp/v2/pages?tags=2068"}, {"href": "https://estreetshuffle.com/index.php/wp-json/wp/v2/jetpack-portfolio?tags=2068"}], "curies": [{"name": "wp", "href": "https://api.w.org/{rel}", "templated": true}]}}, {"id": 1434, "count": 2, "description": "", "link": "https://estreetshuffle.com/index.php/tag/mitch-ryder/", "name": "Mitch Ryder", "slug": "mitch-ryder", "taxonomy": "post_tag", "meta": [], "_links": {"self": [{"href": "https://estreetshuffle.com/index.php/wp-json/wp/v2/tags/1434", "targetHints": {"allow": ["GET"]}}], "collection": [{"href": "https://estreetshuffle.com/index.php/wp-json/wp/v2/tags"}], "about": [{"href": "https://estreetshuffle.com/index.php/wp-json/wp/v2/taxonomies/post_tag"}], "wp:post_type": [{"href": "https://estreetshuffle.com/index.php/wp-json/wp/v2/posts?tags=1434"}, {"href": "https://estreetshuffle.com/index.php/wp-json/wp/v2/pages?tags=1434"}, {"href": "https://estreetshuffle.com/index.php/wp-json/wp/v2/jetpack-portfolio?tags=1434"}], "curies": [{"name": "wp", "href": "https://api.w.org/{rel}", "templated": true}]}}]